{"generated_at": "2026-07-16T17:00:58.414869+00:00", "latest_snapshot": "2026-07-16T18:00:03.270689+01:00", "previous": {"snapshot": "2026-07-16T15:00:03.905476+01:00", "total": 1552563, "by_category": {"Streamer University": 345179, "League of Legends": 271605, "Just Chatting": 201899, "Grand Theft Auto V": 95627, "Dota 2": 85910, "VALORANT": 68452, "Counter-Strike": 63641, "Palworld": 59310, "Rust": 51421, "IRL": 48283, "Fortnite": 31373, "Apex Legends": 30533, "Minecraft": 29844, "Overwatch": 31501, "Dead by Daylight": 28329, "Echoes of Aincrad": 28560, "Hearthstone": 26156, "Monster Hunter Wilds": 21081, "MECCHA CHAMELEON": 16897, "World of Warcraft": 16962}}, "current": [{"category": "Streamer University", "rank": 1, "viewership": 499930, "top10_pct": 67.2}, {"category": "Just Chatting", "rank": 2, "viewership": 305209, "top10_pct": 19.8}, {"category": "Grand Theft Auto V", "rank": 3, "viewership": 114692, "top10_pct": 34.0}, {"category": "VALORANT", "rank": 4, "viewership": 104639, "top10_pct": 42.9}, {"category": "Counter-Strike", "rank": 5, "viewership": 96119, "top10_pct": 50.8}, {"category": "League of Legends", "rank": 6, "viewership": 91749, "top10_pct": 43.3}, {"category": "Palworld", "rank": 7, "viewership": 85219, "top10_pct": 51.4}, {"category": "IRL", "rank": 8, "viewership": 83928, "top10_pct": 54.9}, {"category": "Fortnite", "rank": 9, "viewership": 71700, "top10_pct": 45.3}, {"category": "Minecraft", "rank": 10, "viewership": 64655, "top10_pct": 63.2}, {"category": "Rust", "rank": 11, "viewership": 48958, "top10_pct": 87.7}, {"category": "Dota 2", "rank": 12, "viewership": 41843, "top10_pct": 66.9}, {"category": "Welcome to the Game III", "rank": 13, "viewership": 42951, "top10_pct": 95.3}, {"category": "Overwatch", "rank": 14, "viewership": 33197, "top10_pct": 62.9}, {"category": "Dead by Daylight", "rank": 15, "viewership": 27860, "top10_pct": 45.3}, {"category": "World of Warcraft", "rank": 16, "viewership": 28651, "top10_pct": 41.4}, {"category": "MECCHA CHAMELEON", "rank": 17, "viewership": 26602, "top10_pct": 75.7}, {"category": "Hearthstone", "rank": 18, "viewership": 26306, "top10_pct": 86.9}, {"category": "Call of Duty: Warzone", "rank": 19, "viewership": 24120, "top10_pct": 45.9}, {"category": "Slots", "rank": 20, "viewership": 24006, "top10_pct": 58.2}], "streamers": {"Streamer University": [{"rank": 1, "name": "stableronaldo", "viewers": 85923, "share_pct": 17.2}, {"rank": 2, "name": "Lacy", "viewers": 44588, "share_pct": 8.9}, {"rank": 3, "name": "jasontheween", "viewers": 33944, "share_pct": 6.8}, {"rank": 4, "name": "YonnaJay", "viewers": 33502, "share_pct": 6.7}, {"rank": 5, "name": "KanelJoseph", "viewers": 30017, "share_pct": 6.0}, {"rank": 6, "name": "Agent00", "viewers": 29405, "share_pct": 5.9}, {"rank": 7, "name": "Cinna", "viewers": 23260, "share_pct": 4.7}, {"rank": 8, "name": "wardrobewinter", "viewers": 20337, "share_pct": 4.1}, {"rank": 9, "name": "Ludwig", "viewers": 19558, "share_pct": 3.9}, {"rank": 10, "name": "Marlon", "viewers": 15502, "share_pct": 3.1}], "Just Chatting": [{"rank": 1, "name": "Nix", "viewers": 14613, "share_pct": 4.8}, {"rank": 2, "name": "Stray228", "viewers": 11316, "share_pct": 3.7}, {"rank": 3, "name": "Nmplol", "viewers": 10832, "share_pct": 3.5}, {"rank": 4, "name": "Northernlion", "viewers": 10173, "share_pct": 3.3}, {"rank": 5, "name": "angryginge13", "viewers": 6870, "share_pct": 2.3}, {"rank": 6, "name": "xRohat", "viewers": 6554, "share_pct": 2.1}], "Grand Theft Auto V": [{"rank": 1, "name": "\u53f6\u3061\u3083\u3093\u306d\u308b", "viewers": 19898, "share_pct": 17.3}, {"rank": 2, "name": "Mannyy", "viewers": 2963, "share_pct": 2.6}, {"rank": 3, "name": "\u689f\u96c4\u3057\u308d\u3084", "viewers": 2716, "share_pct": 2.4}, {"rank": 4, "name": "PIRA_real", "viewers": 2374, "share_pct": 2.1}, {"rank": 5, "name": "\u3057\u308d\u307e\u3093\u305f", "viewers": 2125, "share_pct": 1.9}, {"rank": 6, "name": "HuaHed", "viewers": 2088, "share_pct": 1.8}, {"rank": 7, "name": "\u5207\u561b", "viewers": 2000, "share_pct": 1.7}, {"rank": 8, "name": "\u307f\u3064\u304d\u3055\u3093\u3067\u3059", "viewers": 1842, "share_pct": 1.6}, {"rank": 9, "name": "bew_camel", "viewers": 1818, "share_pct": 1.6}, {"rank": 10, "name": "Leenza522", "viewers": 1155, "share_pct": 1.0}], "VALORANT": [{"rank": 1, "name": "VALORANT_EMEA", "viewers": 11393, "share_pct": 10.9}, {"rank": 2, "name": "Sliggytv", "viewers": 5631, "share_pct": 5.4}, {"rank": 3, "name": "Mixwell", "viewers": 5355, "share_pct": 5.1}, {"rank": 4, "name": "beyAz", "viewers": 3637, "share_pct": 3.5}, {"rank": 5, "name": "yue_san", "viewers": 3325, "share_pct": 3.2}, {"rank": 6, "name": "VALORANT_fr", "viewers": 3314, "share_pct": 3.2}, {"rank": 7, "name": "Lazvell", "viewers": 3216, "share_pct": 3.1}, {"rank": 8, "name": "aspaszin", "viewers": 3188, "share_pct": 3.0}, {"rank": 9, "name": "\u4e16\u8aa0", "viewers": 3003, "share_pct": 2.9}, {"rank": 10, "name": "fugu_fps", "viewers": 2869, "share_pct": 2.7}], "Counter-Strike": [{"rank": 1, "name": "buster", "viewers": 31424, "share_pct": 32.7}, {"rank": 2, "name": "CaseBattle_Official", "viewers": 3582, "share_pct": 3.7}, {"rank": 3, "name": "xhocii", "viewers": 3195, "share_pct": 3.3}, {"rank": 4, "name": "MrDzinold", "viewers": 2428, "share_pct": 2.5}, {"rank": 5, "name": "hypetried", "viewers": 2277, "share_pct": 2.4}, {"rank": 6, "name": "LRU_ROSE", "viewers": 1741, "share_pct": 1.8}, {"rank": 7, "name": "fl0m", "viewers": 1558, "share_pct": 1.6}, {"rank": 8, "name": "wastzera", "viewers": 1483, "share_pct": 1.5}, {"rank": 9, "name": "fANDERCS", "viewers": 1171, "share_pct": 1.2}], "League of Legends": [{"rank": 1, "name": "Thebausffs", "viewers": 12074, "share_pct": 13.2}, {"rank": 2, "name": "Caedrel247", "viewers": 8796, "share_pct": 9.6}, {"rank": 3, "name": "Skyyart", "viewers": 3251, "share_pct": 3.5}, {"rank": 4, "name": "lol_nemesis", "viewers": 2712, "share_pct": 3.0}, {"rank": 5, "name": "Tolkin", "viewers": 2544, "share_pct": 2.8}, {"rank": 6, "name": "Nisqyy", "viewers": 2291, "share_pct": 2.5}, {"rank": 7, "name": "NattyNattLoL", "viewers": 2273, "share_pct": 2.5}, {"rank": 8, "name": "LES", "viewers": 2247, "share_pct": 2.4}, {"rank": 9, "name": "Werlyb", "viewers": 1811, "share_pct": 2.0}, {"rank": 10, "name": "EintrachtSpandau", "viewers": 1748, "share_pct": 1.9}], "Palworld": [{"rank": 1, "name": "HutchMF", "viewers": 6178, "share_pct": 7.2}, {"rank": 2, "name": "Gingy", "viewers": 6094, "share_pct": 7.2}, {"rank": 3, "name": "Quin69", "viewers": 6047, "share_pct": 7.1}, {"rank": 4, "name": "knekro", "viewers": 5986, "share_pct": 7.0}, {"rank": 5, "name": "CohhCarnage", "viewers": 5307, "share_pct": 6.2}, {"rank": 6, "name": "MichiMochievee", "viewers": 4636, "share_pct": 5.4}, {"rank": 7, "name": "Nikof", "viewers": 2672, "share_pct": 3.1}, {"rank": 8, "name": "SPYGEA", "viewers": 2586, "share_pct": 3.0}, {"rank": 9, "name": "cloakzy", "viewers": 2207, "share_pct": 2.6}, {"rank": 10, "name": "DansGaming", "viewers": 2072, "share_pct": 2.4}], "IRL": [{"rank": 1, "name": "anarabdullaev", "viewers": 23572, "share_pct": 28.1}, {"rank": 2, "name": "Nicistemmler", "viewers": 3672, "share_pct": 4.4}, {"rank": 3, "name": "jcorko_", "viewers": 3391, "share_pct": 4.0}, {"rank": 4, "name": "Kunshikitty", "viewers": 2823, "share_pct": 3.4}, {"rank": 5, "name": "llunaclark", "viewers": 2238, "share_pct": 2.7}, {"rank": 6, "name": "ronnyberger", "viewers": 2225, "share_pct": 2.7}, {"rank": 7, "name": "TwitchFarming", "viewers": 2200, "share_pct": 2.6}, {"rank": 8, "name": "ReneKreher", "viewers": 2052, "share_pct": 2.4}, {"rank": 9, "name": "reneredo", "viewers": 2026, "share_pct": 2.4}, {"rank": 10, "name": "jakeydavies", "viewers": 1854, "share_pct": 2.2}], "Fortnite": [{"rank": 1, "name": "HappyHappyGal", "viewers": 9306, "share_pct": 13.0}, {"rank": 2, "name": "AussieAntics", "viewers": 4258, "share_pct": 5.9}, {"rank": 3, "name": "MrSavage", "viewers": 3737, "share_pct": 5.2}, {"rank": 4, "name": "NeZaK_", "viewers": 3437, "share_pct": 4.8}, {"rank": 5, "name": "NickEh30", "viewers": 2871, "share_pct": 4.0}, {"rank": 6, "name": "At0m", "viewers": 1993, "share_pct": 2.8}, {"rank": 7, "name": "TooseFN", "viewers": 1958, "share_pct": 2.7}, {"rank": 8, "name": "rezonfn", "viewers": 1679, "share_pct": 2.3}, {"rank": 9, "name": "SypherPK", "viewers": 1677, "share_pct": 2.3}, {"rank": 10, "name": "Mongraal", "viewers": 1565, "share_pct": 2.2}], "Minecraft": [{"rank": 1, "name": "T2x2", "viewers": 14865, "share_pct": 23.0}, {"rank": 2, "name": "5opka", "viewers": 8044, "share_pct": 12.4}, {"rank": 3, "name": "Laink", "viewers": 4782, "share_pct": 7.4}, {"rank": 4, "name": "coldified", "viewers": 4389, "share_pct": 6.8}, {"rank": 5, "name": "\u5922\u91ce\u3042\u304b\u308a", "viewers": 2858, "share_pct": 4.4}, {"rank": 6, "name": "XAH0B", "viewers": 1517, "share_pct": 2.3}, {"rank": 7, "name": "TheGuill84", "viewers": 1381, "share_pct": 2.1}, {"rank": 8, "name": "Spongs_", "viewers": 1059, "share_pct": 1.6}, {"rank": 9, "name": "saps", "viewers": 1017, "share_pct": 1.6}, {"rank": 10, "name": "PWGood", "viewers": 936, "share_pct": 1.4}], "Rust": [{"rank": 1, "name": "\u52a0\u85e4\u7d14\u4e00\u3046\u3093\u3007\u3061\u3083\u3093", "viewers": 34883, "share_pct": 71.3}, {"rank": 2, "name": "Oilrats", "viewers": 3348, "share_pct": 6.8}, {"rank": 3, "name": "IsVolcano", "viewers": 1349, "share_pct": 2.8}, {"rank": 4, "name": "chistobzdenko", "viewers": 919, "share_pct": 1.9}, {"rank": 5, "name": "Tabsy", "viewers": 627, "share_pct": 1.3}, {"rank": 6, "name": "s3kox", "viewers": 478, "share_pct": 1.0}, {"rank": 7, "name": "xXxTheFocuSxXx", "viewers": 374, "share_pct": 0.8}, {"rank": 8, "name": "Cezzy", "viewers": 356, "share_pct": 0.7}, {"rank": 9, "name": "dianaxanton", "viewers": 346, "share_pct": 0.7}, {"rank": 10, "name": "PostyWaitingRoom", "viewers": 280, "share_pct": 0.6}], "Dota 2": [{"rank": 1, "name": "just_ns", "viewers": 5169, "share_pct": 12.4}, {"rank": 2, "name": "avice", "viewers": 5146, "share_pct": 12.3}, {"rank": 3, "name": "serega_pirat", "viewers": 3584, "share_pct": 8.6}, {"rank": 4, "name": "Daxak", "viewers": 3220, "share_pct": 7.7}, {"rank": 5, "name": "Arteezy", "viewers": 3022, "share_pct": 7.2}, {"rank": 6, "name": "qojqva", "viewers": 2079, "share_pct": 5.0}, {"rank": 7, "name": "EWC_LegionGauntlet_EN", "viewers": 1695, "share_pct": 4.1}, {"rank": 8, "name": "misolo3", "viewers": 1443, "share_pct": 3.4}, {"rank": 9, "name": "Quinndota", "viewers": 1413, "share_pct": 3.4}, {"rank": 10, "name": "WitchBlvde", "viewers": 1220, "share_pct": 2.9}], "Welcome to the Game III": [{"rank": 1, "name": "Elajjaz", "viewers": 11062, "share_pct": 25.8}, {"rank": 2, "name": "forsen", "viewers": 7983, "share_pct": 18.6}, {"rank": 3, "name": "Insym", "viewers": 7080, "share_pct": 16.5}, {"rank": 4, "name": "Distortion2", "viewers": 4993, "share_pct": 11.6}, {"rank": 5, "name": "MasterSnakou", "viewers": 2842, "share_pct": 6.6}, {"rank": 6, "name": "Slayproxx", "viewers": 2256, "share_pct": 5.3}, {"rank": 7, "name": "Bawkbasoup", "viewers": 2001, "share_pct": 4.7}, {"rank": 8, "name": "Schwabbeltown", "viewers": 1484, "share_pct": 3.5}, {"rank": 9, "name": "Robbaz", "viewers": 666, "share_pct": 1.6}, {"rank": 10, "name": "DJboucherie", "viewers": 551, "share_pct": 1.3}], "Overwatch": [{"rank": 1, "name": "Emongg", "viewers": 8221, "share_pct": 24.8}, {"rank": 2, "name": "Aspen", "viewers": 4941, "share_pct": 14.9}, {"rank": 3, "name": "mL7support", "viewers": 2613, "share_pct": 7.9}, {"rank": 4, "name": "Toniki", "viewers": 1806, "share_pct": 5.4}, {"rank": 5, "name": "ksg_1912", "viewers": 940, "share_pct": 2.8}, {"rank": 6, "name": "hadi_ow", "viewers": 541, "share_pct": 1.6}, {"rank": 7, "name": "AngrodTralari", "viewers": 479, "share_pct": 1.4}, {"rank": 8, "name": "JOYSTICK", "viewers": 472, "share_pct": 1.4}, {"rank": 9, "name": "ZBRA", "viewers": 458, "share_pct": 1.4}, {"rank": 10, "name": "Txao", "viewers": 416, "share_pct": 1.3}], "Dead by Daylight": [{"rank": 1, "name": "Slate", "viewers": 2043, "share_pct": 7.3}, {"rank": 2, "name": "KnightLight", "viewers": 1873, "share_pct": 6.7}, {"rank": 3, "name": "\u8e22\u8667", "viewers": 1832, "share_pct": 6.6}, {"rank": 4, "name": "Mulder", "viewers": 1508, "share_pct": 5.4}, {"rank": 5, "name": "MatthewSantoro", "viewers": 1179, "share_pct": 4.2}, {"rank": 6, "name": "darkzelk", "viewers": 1030, "share_pct": 3.7}, {"rank": 7, "name": "Gh0stArcade", "viewers": 1019, "share_pct": 3.7}, {"rank": 8, "name": "Mish", "viewers": 970, "share_pct": 3.5}, {"rank": 9, "name": "zepher", "viewers": 617, "share_pct": 2.2}, {"rank": 10, "name": "ANGRYPUG", "viewers": 542, "share_pct": 1.9}], "World of Warcraft": [{"rank": 1, "name": "Altair", "viewers": 2808, "share_pct": 9.8}, {"rank": 2, "name": "Xaryu", "viewers": 2240, "share_pct": 7.8}, {"rank": 3, "name": "ahmpy", "viewers": 1967, "share_pct": 6.9}, {"rank": 4, "name": "Ziqoftw", "viewers": 1231, "share_pct": 4.3}, {"rank": 5, "name": "Mirlol", "viewers": 963, "share_pct": 3.4}, {"rank": 6, "name": "Towelliee", "viewers": 636, "share_pct": 2.2}, {"rank": 7, "name": "meepmonkmw", "viewers": 558, "share_pct": 1.9}, {"rank": 8, "name": "zorthas", "viewers": 548, "share_pct": 1.9}, {"rank": 9, "name": "Shobek", "viewers": 507, "share_pct": 1.8}, {"rank": 10, "name": "Arukori", "viewers": 414, "share_pct": 1.4}], "MECCHA CHAMELEON": [{"rank": 1, "name": "morphe_ya", "viewers": 9062, "share_pct": 34.1}, {"rank": 2, "name": "Dhalucard", "viewers": 4296, "share_pct": 16.1}, {"rank": 3, "name": "singsing", "viewers": 2262, "share_pct": 8.5}, {"rank": 4, "name": "Deadlyslob", "viewers": 1506, "share_pct": 5.7}, {"rank": 5, "name": "TrilluXe", "viewers": 657, "share_pct": 2.5}, {"rank": 6, "name": "TheKller", "viewers": 625, "share_pct": 2.3}, {"rank": 7, "name": "JuiceRewards", "viewers": 574, "share_pct": 2.2}, {"rank": 8, "name": "Farbenfuchs", "viewers": 399, "share_pct": 1.5}, {"rank": 9, "name": "VulpesHD", "viewers": 376, "share_pct": 1.4}, {"rank": 10, "name": "TheFancieMan", "viewers": 371, "share_pct": 1.4}], "Hearthstone": [{"rank": 1, "name": "\u7f85\u5091", "viewers": 7319, "share_pct": 27.8}, {"rank": 2, "name": "PlayHearthstone", "viewers": 6398, "share_pct": 24.3}, {"rank": 3, "name": "RduLIVE", "viewers": 2788, "share_pct": 10.6}, {"rank": 4, "name": "SolaryHS", "viewers": 1869, "share_pct": 7.1}, {"rank": 5, "name": "GuDDummit", "viewers": 1861, "share_pct": 7.1}, {"rank": 6, "name": "DoseofCoffee", "viewers": 618, "share_pct": 2.3}, {"rank": 7, "name": "reqvam", "viewers": 612, "share_pct": 2.3}, {"rank": 8, "name": "Rarran", "viewers": 488, "share_pct": 1.9}, {"rank": 9, "name": "\u9999\u83dc51121", "viewers": 461, "share_pct": 1.8}, {"rank": 10, "name": "\u9f4a\u529b\u65b7\u91d1", "viewers": 433, "share_pct": 1.6}], "Call of Duty: Warzone": [{"rank": 1, "name": "Camy", "viewers": 2970, "share_pct": 12.3}, {"rank": 2, "name": "deusamir", "viewers": 1588, "share_pct": 6.6}, {"rank": 3, "name": "Repullze", "viewers": 1451, "share_pct": 6.0}, {"rank": 4, "name": "Enkeo_", "viewers": 1247, "share_pct": 5.2}, {"rank": 5, "name": "Donkaaklijn", "viewers": 1213, "share_pct": 5.0}, {"rank": 6, "name": "MPX_Player", "viewers": 974, "share_pct": 4.0}, {"rank": 7, "name": "TeePee", "viewers": 897, "share_pct": 3.7}, {"rank": 8, "name": "Aydan", "viewers": 734, "share_pct": 3.0}], "Slots": [{"rank": 1, "name": "orangemorange", "viewers": 3571, "share_pct": 14.9}, {"rank": 2, "name": "Scurrows", "viewers": 2328, "share_pct": 9.7}, {"rank": 3, "name": "SweetFlipsGG", "viewers": 1833, "share_pct": 7.6}, {"rank": 4, "name": "itsAssiTV", "viewers": 1641, "share_pct": 6.8}, {"rank": 5, "name": "BetzTrigg", "viewers": 1067, "share_pct": 4.4}, {"rank": 6, "name": "CasinoDaddy", "viewers": 808, "share_pct": 3.4}, {"rank": 7, "name": "tsk8", "viewers": 739, "share_pct": 3.1}, {"rank": 8, "name": "Teukka", "viewers": 685, "share_pct": 2.9}, {"rank": 9, "name": "vaderffps", "viewers": 681, "share_pct": 2.8}, {"rank": 10, "name": "GODMOTA", "viewers": 608, "share_pct": 2.5}], "World of Tanks": [{"rank": 1, "name": "QuickyBaby", "viewers": 6746, "share_pct": 28.1}, {"rank": 2, "name": "skill4ltu", "viewers": 3832, "share_pct": 15.9}, {"rank": 3, "name": "Dakillzor", "viewers": 2513, "share_pct": 10.5}, {"rank": 4, "name": "Mouzakrobat", "viewers": 2156, "share_pct": 9.0}, {"rank": 5, "name": "KorbenDetka", "viewers": 921, "share_pct": 3.8}, {"rank": 6, "name": "Fr3ddy", "viewers": 728, "share_pct": 3.0}, {"rank": 7, "name": "cyganzor", "viewers": 716, "share_pct": 3.0}, {"rank": 8, "name": "Tankelit", "viewers": 563, "share_pct": 2.3}, {"rank": 9, "name": "MrScheff", "viewers": 503, "share_pct": 2.1}, {"rank": 10, "name": "NewMultiShow", "viewers": 375, "share_pct": 1.6}], "Marvel Rivals": [{"rank": 1, "name": "bogur", "viewers": 2247, "share_pct": 10.8}, {"rank": 2, "name": "kragiee", "viewers": 1596, "share_pct": 7.7}, {"rank": 3, "name": "Symfuhny", "viewers": 1506, "share_pct": 7.2}, {"rank": 4, "name": "m0xyy", "viewers": 1348, "share_pct": 6.5}, {"rank": 5, "name": "SOMJUU", "viewers": 667, "share_pct": 3.2}, {"rank": 6, "name": "VirtualGemma", "viewers": 611, "share_pct": 2.9}, {"rank": 7, "name": "kayjii", "viewers": 603, "share_pct": 2.9}, {"rank": 8, "name": "Ashlyne", "viewers": 419, "share_pct": 2.0}, {"rank": 9, "name": "CringeAlarm", "viewers": 417, "share_pct": 2.0}, {"rank": 10, "name": "whyAndr3w", "viewers": 357, "share_pct": 1.7}], "Escape from Tarkov": [{"rank": 1, "name": "Recrent", "viewers": 5488, "share_pct": 24.9}, {"rank": 2, "name": "Dunduk", "viewers": 1946, "share_pct": 8.8}, {"rank": 3, "name": "WillerZ", "viewers": 1447, "share_pct": 6.6}, {"rank": 4, "name": "Tigz", "viewers": 1237, "share_pct": 5.6}, {"rank": 5, "name": "BULLSEYE", "viewers": 893, "share_pct": 4.0}, {"rank": 6, "name": "knueppelpaste", "viewers": 788, "share_pct": 3.6}, {"rank": 7, "name": "NoGenerals", "viewers": 786, "share_pct": 3.6}, {"rank": 8, "name": "MAZONI", "viewers": 747, "share_pct": 3.4}, {"rank": 9, "name": "Killin9Hit", "viewers": 644, "share_pct": 2.9}, {"rank": 10, "name": "MoMaN", "viewers": 639, "share_pct": 2.9}], "Rainbow Six Siege": [{"rank": 1, "name": "Rainbow6", "viewers": 13859, "share_pct": 66.2}, {"rank": 2, "name": "NICKMERCS", "viewers": 4255, "share_pct": 20.3}, {"rank": 3, "name": "Rainbow6BR", "viewers": 380, "share_pct": 1.8}, {"rank": 4, "name": "VarsityGaming", "viewers": 278, "share_pct": 1.3}, {"rank": 5, "name": "Dreamleslife", "viewers": 177, "share_pct": 0.8}, {"rank": 6, "name": "JosephB93", "viewers": 108, "share_pct": 0.5}, {"rank": 7, "name": "budegadeleao", "viewers": 103, "share_pct": 0.5}, {"rank": 8, "name": "Mint", "viewers": 88, "share_pct": 0.4}, {"rank": 9, "name": "OneShooter", "viewers": 76, "share_pct": 0.4}, {"rank": 10, "name": "foJiG", "viewers": 38, "share_pct": 0.2}], "Assassin's Creed Black Flag Resynced": [{"rank": 1, "name": "MissMikkaa", "viewers": 3823, "share_pct": 18.7}, {"rank": 2, "name": "XababTV", "viewers": 1390, "share_pct": 6.8}, {"rank": 3, "name": "Giantwaffle", "viewers": 1128, "share_pct": 5.5}, {"rank": 4, "name": "fustler", "viewers": 1062, "share_pct": 5.2}, {"rank": 5, "name": "OneRandomDolly", "viewers": 810, "share_pct": 4.0}, {"rank": 6, "name": "airiesummer", "viewers": 628, "share_pct": 3.1}, {"rank": 7, "name": "LIZZ", "viewers": 615, "share_pct": 3.0}, {"rank": 8, "name": "Rodnoy", "viewers": 576, "share_pct": 2.8}, {"rank": 9, "name": "Wisethug", "viewers": 574, "share_pct": 2.8}, {"rank": 10, "name": "ProErsiin", "viewers": 420, "share_pct": 2.0}], "EA Sports FC 26": [{"rank": 1, "name": "TheFutAccountant", "viewers": 8505, "share_pct": 39.9}, {"rank": 2, "name": "AuzioMF", "viewers": 3104, "share_pct": 14.6}, {"rank": 3, "name": "En3rix_", "viewers": 1451, "share_pct": 6.8}, {"rank": 4, "name": "chigre", "viewers": 712, "share_pct": 3.3}, {"rank": 5, "name": "Zazzone230", "viewers": 541, "share_pct": 2.5}, {"rank": 6, "name": "Flokox", "viewers": 455, "share_pct": 2.1}, {"rank": 7, "name": "AnthonyDayTV", "viewers": 405, "share_pct": 1.9}, {"rank": 8, "name": "Chinoir", "viewers": 292, "share_pct": 1.4}, {"rank": 9, "name": "nino_ohne_meinung", "viewers": 265, "share_pct": 1.2}], "The Sims 4": [{"rank": 1, "name": "zarbex", "viewers": 18195, "share_pct": 93.6}, {"rank": 2, "name": "Cissouryne", "viewers": 257, "share_pct": 1.3}, {"rank": 3, "name": "Quel", "viewers": 141, "share_pct": 0.7}, {"rank": 4, "name": "zefrine", "viewers": 129, "share_pct": 0.7}, {"rank": 5, "name": "zasims", "viewers": 96, "share_pct": 0.5}, {"rank": 6, "name": "JaglezYT", "viewers": 82, "share_pct": 0.4}, {"rank": 7, "name": "virsancte", "viewers": 75, "share_pct": 0.4}, {"rank": 8, "name": "piscestrait", "viewers": 61, "share_pct": 0.3}, {"rank": 9, "name": "MightyShanos", "viewers": 46, "share_pct": 0.2}, {"rank": 10, "name": "teknikolour", "viewers": 39, "share_pct": 0.2}], "Apex Legends": [{"rank": 1, "name": "Mande", "viewers": 3298, "share_pct": 22.5}, {"rank": 2, "name": "9impulse", "viewers": 819, "share_pct": 5.6}, {"rank": 3, "name": "tttcheekyttt", "viewers": 647, "share_pct": 4.4}, {"rank": 4, "name": "Sang", "viewers": 584, "share_pct": 4.0}, {"rank": 5, "name": "dttodot", "viewers": 568, "share_pct": 3.9}, {"rank": 6, "name": "claraatwork", "viewers": 472, "share_pct": 3.2}, {"rank": 7, "name": "17baby17lol", "viewers": 399, "share_pct": 2.7}, {"rank": 8, "name": "Keon", "viewers": 380, "share_pct": 2.6}, {"rank": 9, "name": "KSWINNIIE", "viewers": 307, "share_pct": 2.1}], "Call of Duty: Black Ops II": [{"rank": 1, "name": "therealskylergamer", "viewers": 9139, "share_pct": 56.5}, {"rank": 2, "name": "Riirex", "viewers": 1278, "share_pct": 7.9}, {"rank": 3, "name": "FalaXii", "viewers": 927, "share_pct": 5.7}, {"rank": 4, "name": "aXoZer", "viewers": 902, "share_pct": 5.6}, {"rank": 5, "name": "Swagg", "viewers": 709, "share_pct": 4.4}, {"rank": 6, "name": "MrSoki", "viewers": 665, "share_pct": 4.1}, {"rank": 7, "name": "LaughtedTwo", "viewers": 257, "share_pct": 1.6}, {"rank": 8, "name": "Emzy", "viewers": 223, "share_pct": 1.4}, {"rank": 9, "name": "vStats", "viewers": 160, "share_pct": 1.0}, {"rank": 10, "name": "Bubblegum", "viewers": 152, "share_pct": 0.9}], "DJs": [{"rank": 1, "name": "LissyMusic", "viewers": 3244, "share_pct": 26.4}, {"rank": 2, "name": "PeiKa_Official", "viewers": 1389, "share_pct": 11.3}, {"rank": 3, "name": "Nyny_x", "viewers": 461, "share_pct": 3.7}, {"rank": 4, "name": "SalvuccioDJ", "viewers": 457, "share_pct": 3.7}, {"rank": 5, "name": "HotBeatsTV", "viewers": 450, "share_pct": 3.7}, {"rank": 6, "name": "Colaway", "viewers": 302, "share_pct": 2.5}, {"rank": 7, "name": "Sam_Tweaks", "viewers": 250, "share_pct": 2.0}, {"rank": 8, "name": "Infected_Fay", "viewers": 185, "share_pct": 1.5}, {"rank": 9, "name": "Hard_Music_TV", "viewers": 179, "share_pct": 1.5}, {"rank": 10, "name": "JohnBBeta", "viewers": 169, "share_pct": 1.4}], "Monster Hunter Wilds": [{"rank": 1, "name": "fps_shaka", "viewers": 11138, "share_pct": 92.5}, {"rank": 2, "name": "Vycery", "viewers": 131, "share_pct": 1.1}, {"rank": 3, "name": "SimplyOzzy", "viewers": 92, "share_pct": 0.8}, {"rank": 4, "name": "OmakKong", "viewers": 73, "share_pct": 0.6}, {"rank": 5, "name": "AngBata11", "viewers": 64, "share_pct": 0.5}, {"rank": 6, "name": "\u304a\u3071\u3093\u3061\u3085\u3071\u3050", "viewers": 41, "share_pct": 0.3}, {"rank": 7, "name": "Henrietta_00", "viewers": 37, "share_pct": 0.3}, {"rank": 8, "name": "Sanya_Shut_", "viewers": 30, "share_pct": 0.2}, {"rank": 9, "name": "\u7d05\u8336\u3046\u307e\u3044", "viewers": 28, "share_pct": 0.2}, {"rank": 10, "name": "kazane_lia", "viewers": 26, "share_pct": 0.2}], "ARKNIGHTS: ENDFIELD": [{"rank": 1, "name": "BadgeNotify", "viewers": 4554, "share_pct": 37.9}, {"rank": 2, "name": "vixi", "viewers": 783, "share_pct": 6.5}, {"rank": 3, "name": "elis", "viewers": 426, "share_pct": 3.5}, {"rank": 4, "name": "ZG__", "viewers": 351, "share_pct": 2.9}, {"rank": 5, "name": "yenkoes", "viewers": 321, "share_pct": 2.7}, {"rank": 6, "name": "oFuris", "viewers": 310, "share_pct": 2.6}, {"rank": 7, "name": "AxeSay7", "viewers": 290, "share_pct": 2.4}, {"rank": 8, "name": "FLlES", "viewers": 263, "share_pct": 2.2}, {"rank": 9, "name": "SmugSlav", "viewers": 256, "share_pct": 2.1}, {"rank": 10, "name": "\u7490\u6d1b\u6d1b", "viewers": 254, "share_pct": 2.1}], "Art": [{"rank": 1, "name": "KasumiSen", "viewers": 550, "share_pct": 5.0}, {"rank": 2, "name": "fourleafisland", "viewers": 343, "share_pct": 3.1}, {"rank": 3, "name": "luma_rum", "viewers": 305, "share_pct": 2.8}, {"rank": 4, "name": "cartcorn", "viewers": 198, "share_pct": 1.8}, {"rank": 5, "name": "MorninChai", "viewers": 131, "share_pct": 1.2}, {"rank": 6, "name": "46cm_", "viewers": 123, "share_pct": 1.1}, {"rank": 7, "name": "Sifs", "viewers": 111, "share_pct": 1.0}, {"rank": 8, "name": "cnotbusch", "viewers": 109, "share_pct": 1.0}, {"rank": 9, "name": "JonAwesomeVedo", "viewers": 105, "share_pct": 1.0}, {"rank": 10, "name": "MCroft07", "viewers": 91, "share_pct": 0.8}], "Always On": [{"rank": 1, "name": "TheBurntPeanut_247", "viewers": 2303, "share_pct": 21.5}, {"rank": 2, "name": "CineIlloJuan", "viewers": 837, "share_pct": 7.8}, {"rank": 3, "name": "ChilledChaos", "viewers": 424, "share_pct": 4.0}, {"rank": 4, "name": "LIRIK_247", "viewers": 377, "share_pct": 3.5}, {"rank": 5, "name": "RiffTrax", "viewers": 325, "share_pct": 3.0}, {"rank": 6, "name": "DanGheeslingTV", "viewers": 294, "share_pct": 2.7}, {"rank": 7, "name": "RdcWaitingRoom_", "viewers": 231, "share_pct": 2.2}, {"rank": 8, "name": "YuGiOh_Deutsch", "viewers": 201, "share_pct": 1.9}, {"rank": 9, "name": "Cohh", "viewers": 192, "share_pct": 1.8}, {"rank": 10, "name": "WorstPremadeEver", "viewers": 178, "share_pct": 1.7}], "Delta Force": [{"rank": 1, "name": "\u8d64\u9b3c\u4f2f\u4f2f", "viewers": 1194, "share_pct": 11.5}, {"rank": 2, "name": "tJ_sk1per", "viewers": 1126, "share_pct": 10.8}, {"rank": 3, "name": "\u6ce2\u98a8\u6c34\u96de", "viewers": 1034, "share_pct": 9.9}, {"rank": 4, "name": "restiafps", "viewers": 899, "share_pct": 8.6}, {"rank": 5, "name": "Ren0809k", "viewers": 688, "share_pct": 6.6}, {"rank": 6, "name": "Cyqop", "viewers": 646, "share_pct": 6.2}, {"rank": 7, "name": "RoguePringle", "viewers": 413, "share_pct": 4.0}, {"rank": 8, "name": "APlus0v0", "viewers": 314, "share_pct": 3.0}, {"rank": 9, "name": "\u96ea\u3053\u3086\u304d_\u5e8f\u5883", "viewers": 302, "share_pct": 2.9}, {"rank": 10, "name": "\u6714\u3055\u304f\u308d_\u6708\u8755\u5c4b", "viewers": 220, "share_pct": 2.1}], "ASMR": [{"rank": 1, "name": "HalO_Sweety", "viewers": 1877, "share_pct": 18.3}, {"rank": 2, "name": "\u7434\u4e43\u8449_\u96ea\u4e43", "viewers": 1375, "share_pct": 13.4}, {"rank": 3, "name": "yoursafterdark", "viewers": 1203, "share_pct": 11.7}, {"rank": 4, "name": "Tiffy", "viewers": 957, "share_pct": 9.3}, {"rank": 5, "name": "TheNicoleT", "viewers": 754, "share_pct": 7.4}, {"rank": 6, "name": "LinaLachesis", "viewers": 329, "share_pct": 3.2}, {"rank": 7, "name": "usagikira_", "viewers": 276, "share_pct": 2.7}, {"rank": 8, "name": "SharonQueen", "viewers": 250, "share_pct": 2.4}, {"rank": 9, "name": "Aurorafractubela_uwu", "viewers": 244, "share_pct": 2.4}], "ELDEN RING": [{"rank": 1, "name": "KarmikKoala", "viewers": 2154, "share_pct": 22.6}, {"rank": 2, "name": "pilavpowa", "viewers": 1421, "share_pct": 14.9}, {"rank": 3, "name": "KEMIST_C10H15N", "viewers": 1059, "share_pct": 11.1}, {"rank": 4, "name": "Jack_Fromsoft", "viewers": 601, "share_pct": 6.3}, {"rank": 5, "name": "ShyroBoy", "viewers": 411, "share_pct": 4.3}, {"rank": 6, "name": "Ribozome", "viewers": 260, "share_pct": 2.7}, {"rank": 7, "name": "yuyu_beans", "viewers": 249, "share_pct": 2.6}, {"rank": 8, "name": "kati", "viewers": 202, "share_pct": 2.1}, {"rank": 9, "name": "ELoTRiX_247", "viewers": 157, "share_pct": 1.6}, {"rank": 10, "name": "Teejay", "viewers": 90, "share_pct": 0.9}], "Path of Exile": [{"rank": 1, "name": "fubgun", "viewers": 3451, "share_pct": 38.0}, {"rank": 2, "name": "captainlance9", "viewers": 1198, "share_pct": 13.2}, {"rank": 3, "name": "tytykiller", "viewers": 1145, "share_pct": 12.6}, {"rank": 4, "name": "GhazzyTV", "viewers": 631, "share_pct": 6.9}, {"rank": 5, "name": "\u4f4e\u6b38\u6b7b", "viewers": 564, "share_pct": 6.2}, {"rank": 6, "name": "\u60e1\u9b54\u8c93\u8c93\u8c93", "viewers": 501, "share_pct": 5.5}, {"rank": 7, "name": "KEPA_MITA", "viewers": 376, "share_pct": 4.1}, {"rank": 8, "name": "Tuadh", "viewers": 351, "share_pct": 3.9}, {"rank": 9, "name": "POEGuy007", "viewers": 248, "share_pct": 2.7}, {"rank": 10, "name": "BilalDelValle", "viewers": 237, "share_pct": 2.6}], "Rocket League": [{"rank": 1, "name": "Rezears", "viewers": 1016, "share_pct": 11.6}, {"rank": 2, "name": "Mawkzy_", "viewers": 973, "share_pct": 11.1}, {"rank": 3, "name": "RocketBaguette", "viewers": 905, "share_pct": 10.3}, {"rank": 4, "name": "AlphaKep", "viewers": 723, "share_pct": 8.3}, {"rank": 5, "name": "RxiiRL", "viewers": 401, "share_pct": 4.6}, {"rank": 6, "name": "Feer", "viewers": 372, "share_pct": 4.2}, {"rank": 7, "name": "bruz777", "viewers": 346, "share_pct": 3.9}, {"rank": 8, "name": "TenacityTv", "viewers": 326, "share_pct": 3.7}, {"rank": 9, "name": "Rale11play", "viewers": 280, "share_pct": 3.2}, {"rank": 10, "name": "JamaicanCoconut", "viewers": 270, "share_pct": 3.1}], "Arena Breakout: Infinite": [{"rank": 1, "name": "Arven93", "viewers": 1016, "share_pct": 11.5}, {"rank": 2, "name": "ImOw", "viewers": 1008, "share_pct": 11.4}, {"rank": 3, "name": "Tenkedzu", "viewers": 893, "share_pct": 10.1}, {"rank": 4, "name": "uzorrrr", "viewers": 755, "share_pct": 8.5}, {"rank": 5, "name": "HALFLEX", "viewers": 749, "share_pct": 8.4}, {"rank": 6, "name": "Rxckstar", "viewers": 372, "share_pct": 4.2}, {"rank": 7, "name": "Ralisco", "viewers": 350, "share_pct": 3.9}, {"rank": 8, "name": "Trey24k", "viewers": 247, "share_pct": 2.8}, {"rank": 9, "name": "tontitoortiz", "viewers": 209, "share_pct": 2.4}, {"rank": 10, "name": "off_kuka358", "viewers": 170, "share_pct": 1.9}], "Old School RuneScape": [{"rank": 1, "name": "B0aty", "viewers": 1688, "share_pct": 19.3}, {"rank": 2, "name": "Faux", "viewers": 1385, "share_pct": 15.9}, {"rank": 3, "name": "Sick_Nerd", "viewers": 1087, "share_pct": 12.5}, {"rank": 4, "name": "Muts", "viewers": 647, "share_pct": 7.4}, {"rank": 5, "name": "Mmorpg", "viewers": 494, "share_pct": 5.7}, {"rank": 6, "name": "Roidie", "viewers": 350, "share_pct": 4.0}, {"rank": 7, "name": "Lake", "viewers": 339, "share_pct": 3.9}, {"rank": 8, "name": "Viikonloppu", "viewers": 277, "share_pct": 3.2}, {"rank": 9, "name": "mooky_wooky", "viewers": 236, "share_pct": 2.7}, {"rank": 10, "name": "Megan", "viewers": 193, "share_pct": 2.2}], "Tibia": [{"rank": 1, "name": "livedogoes", "viewers": 892, "share_pct": 10.8}, {"rank": 2, "name": "MassRoon", "viewers": 546, "share_pct": 6.6}, {"rank": 3, "name": "artilh3iro", "viewers": 492, "share_pct": 5.9}, {"rank": 4, "name": "veyllor", "viewers": 309, "share_pct": 3.7}, {"rank": 5, "name": "CharllonLobo", "viewers": 282, "share_pct": 3.4}, {"rank": 6, "name": "Miguelnutt", "viewers": 267, "share_pct": 3.2}, {"rank": 7, "name": "nxxxte", "viewers": 207, "share_pct": 2.5}, {"rank": 8, "name": "Vda_pedro", "viewers": 177, "share_pct": 2.1}, {"rank": 9, "name": "mutilinha", "viewers": 156, "share_pct": 1.9}, {"rank": 10, "name": "xhannytv", "viewers": 147, "share_pct": 1.8}], "PUBG: BATTLEGROUNDS": [{"rank": 1, "name": "\u6db5\u6db50501", "viewers": 1135, "share_pct": 14.4}, {"rank": 2, "name": "SmashLunatic", "viewers": 546, "share_pct": 6.9}, {"rank": 3, "name": "DoktorFroid", "viewers": 433, "share_pct": 5.5}, {"rank": 4, "name": "Corky", "viewers": 258, "share_pct": 3.3}, {"rank": 5, "name": "KILYAKAi_", "viewers": 216, "share_pct": 2.7}, {"rank": 6, "name": "badboyy2k", "viewers": 198, "share_pct": 2.5}, {"rank": 7, "name": "LulaDoPUB", "viewers": 192, "share_pct": 2.4}, {"rank": 8, "name": "allyz1nfps", "viewers": 184, "share_pct": 2.3}, {"rank": 9, "name": "mafiozniklife", "viewers": 178, "share_pct": 2.3}, {"rank": 10, "name": "\u0627\u0644\u0642\u0623\u0626\u062f", "viewers": 169, "share_pct": 2.1}], "Mobile Legends: Bang Bang": [{"rank": 1, "name": "titamin1", "viewers": 1012, "share_pct": 11.8}, {"rank": 2, "name": "oneshotmlbb", "viewers": 962, "share_pct": 11.2}, {"rank": 3, "name": "MLBB_CIS", "viewers": 917, "share_pct": 10.7}, {"rank": 4, "name": "smetanduck", "viewers": 912, "share_pct": 10.6}, {"rank": 5, "name": "GOLDENJET_", "viewers": 864, "share_pct": 10.0}, {"rank": 6, "name": "wizer02", "viewers": 790, "share_pct": 9.2}, {"rank": 7, "name": "k2nnn8", "viewers": 635, "share_pct": 7.4}, {"rank": 8, "name": "Gaules", "viewers": 479, "share_pct": 5.6}, {"rank": 9, "name": "ant1ka", "viewers": 444, "share_pct": 5.2}, {"rank": 10, "name": "Xerxkashi", "viewers": 211, "share_pct": 2.5}], "The Lord of the Rings: The Battle for Middle-earth": [{"rank": 1, "name": "Bonjwa", "viewers": 4741, "share_pct": 59.4}, {"rank": 2, "name": "RocketBeansTV", "viewers": 2437, "share_pct": 30.5}, {"rank": 3, "name": "Back2Warcraft", "viewers": 585, "share_pct": 7.3}, {"rank": 4, "name": "KiaraHier", "viewers": 221, "share_pct": 2.8}, {"rank": 5, "name": "eldo_n_rado", "viewers": 3, "share_pct": 0.0}], "Destiny 2": [{"rank": 1, "name": "Aztecross", "viewers": 3823, "share_pct": 51.5}, {"rank": 2, "name": "Leopard", "viewers": 912, "share_pct": 12.3}, {"rank": 3, "name": "Saltagreppo", "viewers": 269, "share_pct": 3.6}, {"rank": 4, "name": "FalloutPlays", "viewers": 240, "share_pct": 3.2}, {"rank": 5, "name": "Butters", "viewers": 216, "share_pct": 2.9}, {"rank": 6, "name": "ZkMushroom", "viewers": 170, "share_pct": 2.3}, {"rank": 7, "name": "terror", "viewers": 118, "share_pct": 1.6}, {"rank": 8, "name": "Samoan_317", "viewers": 105, "share_pct": 1.4}, {"rank": 9, "name": "SassyGirl1715", "viewers": 86, "share_pct": 1.2}, {"rank": 10, "name": "LUCKYY10P", "viewers": 84, "share_pct": 1.1}], "World of Warships": [{"rank": 1, "name": "WorldofWarships", "viewers": 5949, "share_pct": 79.0}, {"rank": 2, "name": "g4nng", "viewers": 414, "share_pct": 5.5}, {"rank": 3, "name": "ChaosMachineGR", "viewers": 327, "share_pct": 4.3}, {"rank": 4, "name": "Meduzkoo", "viewers": 171, "share_pct": 2.3}, {"rank": 5, "name": "Der7teZwerg_", "viewers": 113, "share_pct": 1.5}, {"rank": 6, "name": "Bl4ckSK", "viewers": 85, "share_pct": 1.1}, {"rank": 7, "name": "CarbineCarlito", "viewers": 76, "share_pct": 1.0}, {"rank": 8, "name": "seadonkeygaming", "viewers": 72, "share_pct": 1.0}, {"rank": 9, "name": "MindOverPixels", "viewers": 62, "share_pct": 0.8}, {"rank": 10, "name": "Stargatesg68", "viewers": 50, "share_pct": 0.7}], "Echoes of Aincrad": [{"rank": 1, "name": "\u30d0\u30c8\u30e9", "viewers": 5506, "share_pct": 75.5}, {"rank": 2, "name": "\u30ae\u30eb\u304f\u3093", "viewers": 539, "share_pct": 7.4}, {"rank": 3, "name": "Ukyochi_JP", "viewers": 452, "share_pct": 6.2}, {"rank": 4, "name": "brutalles", "viewers": 273, "share_pct": 3.7}, {"rank": 5, "name": "WithZack", "viewers": 67, "share_pct": 0.9}, {"rank": 6, "name": "DistractedElf", "viewers": 62, "share_pct": 0.9}, {"rank": 7, "name": "\u6c50\u6d77\u611b\u9e97\u7d72", "viewers": 48, "share_pct": 0.7}, {"rank": 8, "name": "Gremlynnie", "viewers": 33, "share_pct": 0.5}, {"rank": 9, "name": "Miraj_vt", "viewers": 30, "share_pct": 0.4}, {"rank": 10, "name": "Yariva_", "viewers": 23, "share_pct": 0.3}], "ARC Raiders": [{"rank": 1, "name": "ShinyaTheNinja", "viewers": 671, "share_pct": 10.1}, {"rank": 2, "name": "LEV_BRITVAAA", "viewers": 529, "share_pct": 8.0}, {"rank": 3, "name": "TheGamingMerchant", "viewers": 432, "share_pct": 6.5}, {"rank": 4, "name": "VidGUNn", "viewers": 376, "share_pct": 5.7}, {"rank": 5, "name": "nagibatorleon", "viewers": 262, "share_pct": 4.0}, {"rank": 6, "name": "ItsKonax", "viewers": 256, "share_pct": 3.9}, {"rank": 7, "name": "TvJhonson", "viewers": 251, "share_pct": 3.8}, {"rank": 8, "name": "Yuraahh", "viewers": 197, "share_pct": 3.0}, {"rank": 9, "name": "Sangras", "viewers": 197, "share_pct": 3.0}, {"rank": 10, "name": "Reave", "viewers": 195, "share_pct": 2.9}], "Pools, Hot Tubs, and Beaches": [{"rank": 1, "name": "Gilticus", "viewers": 2570, "share_pct": 42.7}, {"rank": 2, "name": "EmjayPlayss", "viewers": 2216, "share_pct": 36.8}, {"rank": 3, "name": "meetenshow", "viewers": 740, "share_pct": 12.3}, {"rank": 4, "name": "Faith", "viewers": 312, "share_pct": 5.2}, {"rank": 5, "name": "JubaGordoTV", "viewers": 215, "share_pct": 3.6}, {"rank": 6, "name": "kartellika", "viewers": 213, "share_pct": 3.5}, {"rank": 7, "name": "KristenLanae", "viewers": 119, "share_pct": 2.0}, {"rank": 8, "name": "destinyfomo", "viewers": 81, "share_pct": 1.3}, {"rank": 9, "name": "lauraluxtv", "viewers": 72, "share_pct": 1.2}, {"rank": 10, "name": "aashhuu", "viewers": 71, "share_pct": 1.2}]}}