{"generated_at": "2026-07-01T11:00:44.548438+00:00", "latest_snapshot": "2026-07-01T12:00:03.654886+01:00", "previous": {"snapshot": "2026-07-01T09:00:03.600915+01:00", "total": 643252, "by_category": {"League of Legends": 178830, "Just Chatting": 108429, "Counter-Strike": 51371, "ELDEN RING NIGHTREIGN": 32562, "Dead by Daylight": 25556, "Dota 2": 26680, "IRL": 25000, "VALORANT": 18189, "Grand Theft Auto V": 18800, "Always On": 20692, "Fortnite": 15969, "Diablo IV": 17501, "Marvel Rivals": 14637, "Hearthstone": 15846, "Overwatch": 13714, "Genshin Impact": 13360, "Powerful Pro Yakyuu 2026-2027": 14324, "Apex Legends": 10924, "Minecraft": 9844, "Sand: Raiders Of Sophie": 11024}}, "current": [{"category": "Just Chatting", "rank": 1, "viewership": 143673, "top10_pct": 27.9}, {"category": "League of Legends", "rank": 2, "viewership": 111787, "top10_pct": 51.2}, {"category": "Counter-Strike", "rank": 3, "viewership": 60037, "top10_pct": 45.8}, {"category": "Grand Theft Auto V", "rank": 4, "viewership": 46699, "top10_pct": 34.5}, {"category": "VALORANT", "rank": 5, "viewership": 28995, "top10_pct": 31.9}, {"category": "Dota 2", "rank": 6, "viewership": 35291, "top10_pct": 61.4}, {"category": "Pok\u00e9mon Champions", "rank": 7, "viewership": 34509, "top10_pct": 97.0}, {"category": "IRL", "rank": 8, "viewership": 27165, "top10_pct": 44.7}, {"category": "Apex Legends", "rank": 9, "viewership": 21776, "top10_pct": 51.2}, {"category": "Dead by Daylight", "rank": 10, "viewership": 20681, "top10_pct": 43.5}, {"category": "Powerful Pro Yakyuu 2026-2027", "rank": 11, "viewership": 21861, "top10_pct": 100.1}, {"category": "MECCHA CHAMELEON", "rank": 12, "viewership": 21245, "top10_pct": 66.6}, {"category": "Diablo IV", "rank": 13, "viewership": 19714, "top10_pct": 67.1}, {"category": "Shine Post: Be Your Idol!", "rank": 14, "viewership": 19470, "top10_pct": 100.0}, {"category": "Hearthstone", "rank": 15, "viewership": 17060, "top10_pct": 68.7}, {"category": "Fortnite", "rank": 16, "viewership": 12389, "top10_pct": 39.3}, {"category": "Always On", "rank": 17, "viewership": 16366, "top10_pct": 59.9}, {"category": "Overwatch", "rank": 18, "viewership": 15369, "top10_pct": 41.7}, {"category": "Genshin Impact", "rank": 19, "viewership": 14103, "top10_pct": 60.9}, {"category": "World of Warcraft", "rank": 20, "viewership": 14041, "top10_pct": 39.3}], "streamers": {"Just Chatting": [{"rank": 1, "name": "\u5e03\u56e3\u3061\u3083\u3093\u3068\u7533\u3057\u307e\u3059", "viewers": 11906, "share_pct": 8.3}, {"rank": 2, "name": "\u3086\u3086\u3046\u305f\u62bc\u5fcd", "viewers": 5333, "share_pct": 3.7}, {"rank": 3, "name": "Jinnytty", "viewers": 4447, "share_pct": 3.1}, {"rank": 4, "name": "Dracon", "viewers": 3764, "share_pct": 2.6}, {"rank": 5, "name": "LOTA", "viewers": 3270, "share_pct": 2.3}, {"rank": 6, "name": "psychedeliacy", "viewers": 3205, "share_pct": 2.2}, {"rank": 7, "name": "nenormova", "viewers": 2980, "share_pct": 2.1}, {"rank": 8, "name": "Juice", "viewers": 2660, "share_pct": 1.9}, {"rank": 9, "name": "nacho_dayo", "viewers": 2513, "share_pct": 1.7}], "League of Legends": [{"rank": 1, "name": "Caedrel247", "viewers": 20204, "share_pct": 18.1}, {"rank": 2, "name": "Jynxzi", "viewers": 11833, "share_pct": 10.6}, {"rank": 3, "name": "otplol_", "viewers": 8905, "share_pct": 8.0}, {"rank": 4, "name": "NeVeR_LosEs", "viewers": 5034, "share_pct": 4.5}, {"rank": 5, "name": "Tolkin", "viewers": 4780, "share_pct": 4.3}, {"rank": 6, "name": "\u4e16\u8aa0", "viewers": 3514, "share_pct": 3.1}, {"rank": 7, "name": "TraYtoNlol", "viewers": 2924, "share_pct": 2.6}], "Counter-Strike": [{"rank": 1, "name": "hypetried", "viewers": 7403, "share_pct": 12.3}, {"rank": 2, "name": "jerry256cs2", "viewers": 4728, "share_pct": 7.9}, {"rank": 3, "name": "des0ut", "viewers": 3510, "share_pct": 5.8}, {"rank": 4, "name": "fissure_cs_b", "viewers": 2594, "share_pct": 4.3}, {"rank": 5, "name": "chopperinho", "viewers": 2377, "share_pct": 4.0}, {"rank": 6, "name": "CroissantStrike", "viewers": 2019, "share_pct": 3.4}, {"rank": 7, "name": "szelioficjalnie", "viewers": 1772, "share_pct": 3.0}, {"rank": 8, "name": "qbaxa", "viewers": 1257, "share_pct": 2.1}, {"rank": 9, "name": "titaanitv", "viewers": 1156, "share_pct": 1.9}, {"rank": 10, "name": "frinnCS", "viewers": 681, "share_pct": 1.1}], "Grand Theft Auto V": [{"rank": 1, "name": "Leenza522", "viewers": 4127, "share_pct": 8.8}, {"rank": 2, "name": "kingdefender_", "viewers": 1627, "share_pct": 3.5}, {"rank": 3, "name": "\u307f\u3064\u304d\u3055\u3093\u3067\u3059", "viewers": 1609, "share_pct": 3.4}, {"rank": 4, "name": "Middleeetv", "viewers": 1482, "share_pct": 3.2}, {"rank": 5, "name": "vanotica_", "viewers": 1392, "share_pct": 3.0}, {"rank": 6, "name": "\u3042\u3069\u307f\u3093", "viewers": 1342, "share_pct": 2.9}, {"rank": 7, "name": "\u3048\u3073\u3059\u304f\u3093", "viewers": 1302, "share_pct": 2.8}, {"rank": 8, "name": "\u30a2\u30b8\u5409", "viewers": 1231, "share_pct": 2.6}, {"rank": 9, "name": "zepher", "viewers": 1071, "share_pct": 2.3}, {"rank": 10, "name": "FOXRABBIT", "viewers": 930, "share_pct": 2.0}], "VALORANT": [{"rank": 1, "name": "\u30ae\u30eb\u304f\u3093", "viewers": 2061, "share_pct": 7.1}, {"rank": 2, "name": "nAts", "viewers": 1879, "share_pct": 6.5}, {"rank": 3, "name": "archangel_hs", "viewers": 1111, "share_pct": 3.8}, {"rank": 4, "name": "Grimm", "viewers": 1024, "share_pct": 3.5}, {"rank": 5, "name": "rAx1337", "viewers": 652, "share_pct": 2.2}, {"rank": 6, "name": "\u5076\u662f\u5747\u4ed4", "viewers": 608, "share_pct": 2.1}, {"rank": 7, "name": "\u3080\u3089\u304a\u304b\u308a\u3070\u30fc", "viewers": 528, "share_pct": 1.8}, {"rank": 8, "name": "shoxieJESUSS", "viewers": 483, "share_pct": 1.7}, {"rank": 9, "name": "Mogi", "viewers": 479, "share_pct": 1.7}, {"rank": 10, "name": "akash1vl", "viewers": 427, "share_pct": 1.5}], "Dota 2": [{"rank": 1, "name": "Topson", "viewers": 8876, "share_pct": 25.2}, {"rank": 2, "name": "AdmiralBulldog", "viewers": 3771, "share_pct": 10.7}, {"rank": 3, "name": "NoctisAK47", "viewers": 1805, "share_pct": 5.1}, {"rank": 4, "name": "Ghostik", "viewers": 1380, "share_pct": 3.9}, {"rank": 5, "name": "rxnexus", "viewers": 1205, "share_pct": 3.4}, {"rank": 6, "name": "JUSTHATEMEEECATQ", "viewers": 1020, "share_pct": 2.9}, {"rank": 7, "name": "ENC", "viewers": 1010, "share_pct": 2.9}, {"rank": 8, "name": "SHEVRONIN", "viewers": 944, "share_pct": 2.7}, {"rank": 9, "name": "seucreysonreborn", "viewers": 846, "share_pct": 2.4}, {"rank": 10, "name": "awfdota", "viewers": 827, "share_pct": 2.3}], "Pok\u00e9mon Champions": [{"rank": 1, "name": "k4sen", "viewers": 11569, "share_pct": 33.5}, {"rank": 2, "name": "\u3050\u3061\u3064\u307c", "viewers": 8348, "share_pct": 24.2}, {"rank": 3, "name": "\u8d64\u898b\u304b\u308b\u3073", "viewers": 3579, "share_pct": 10.4}, {"rank": 4, "name": "\u5982\u6708\u308c\u3093", "viewers": 3273, "share_pct": 9.5}, {"rank": 5, "name": "Lazvell", "viewers": 2613, "share_pct": 7.6}, {"rank": 6, "name": "SAVOGE_GUTITUBO", "viewers": 2122, "share_pct": 6.1}, {"rank": 7, "name": "\u713c\u304d\u30d1\u30f3", "viewers": 761, "share_pct": 2.2}, {"rank": 8, "name": "clutch_fii", "viewers": 585, "share_pct": 1.7}, {"rank": 9, "name": "RavenHS", "viewers": 327, "share_pct": 0.9}, {"rank": 10, "name": "\u305f\u3089\u3053", "viewers": 300, "share_pct": 0.9}], "IRL": [{"rank": 1, "name": "Chloe__IRL", "viewers": 1970, "share_pct": 7.3}, {"rank": 2, "name": "Kunshikitty", "viewers": 1838, "share_pct": 6.8}, {"rank": 3, "name": "knirpz", "viewers": 1811, "share_pct": 6.7}, {"rank": 4, "name": "MinusElf", "viewers": 1453, "share_pct": 5.3}, {"rank": 5, "name": "\u59b2\u59b2\u54ac\u679c\u51cd", "viewers": 1239, "share_pct": 4.6}, {"rank": 6, "name": "INNESHX", "viewers": 909, "share_pct": 3.3}, {"rank": 7, "name": "meetenshow", "viewers": 857, "share_pct": 3.2}, {"rank": 8, "name": "junicats", "viewers": 743, "share_pct": 2.7}, {"rank": 9, "name": "gracehan_", "viewers": 680, "share_pct": 2.5}, {"rank": 10, "name": "LillyTheChilly", "viewers": 647, "share_pct": 2.4}], "Apex Legends": [{"rank": 1, "name": "ImperialHal__", "viewers": 3372, "share_pct": 15.5}, {"rank": 2, "name": "\u6ce2\u98a8\u6c34\u96de", "viewers": 2286, "share_pct": 10.5}, {"rank": 3, "name": "Euriece", "viewers": 1413, "share_pct": 6.5}, {"rank": 4, "name": "Extesyy ", "viewers": 746, "share_pct": 3.4}, {"rank": 5, "name": "\u30d8\u30f3\u30c7\u30a3\u30fc", "viewers": 729, "share_pct": 3.3}, {"rank": 6, "name": "oraxe", "viewers": 659, "share_pct": 3.0}, {"rank": 7, "name": "gdolphn", "viewers": 608, "share_pct": 2.8}, {"rank": 8, "name": "cloudyatnight", "viewers": 562, "share_pct": 2.6}, {"rank": 9, "name": "yamatonjp", "viewers": 480, "share_pct": 2.2}, {"rank": 10, "name": "aud0r", "viewers": 287, "share_pct": 1.3}], "Dead by Daylight": [{"rank": 1, "name": "TheJRM", "viewers": 2386, "share_pct": 11.5}, {"rank": 2, "name": "\u8e22\u8667", "viewers": 1655, "share_pct": 8.0}, {"rank": 3, "name": "LittleSpaceRock", "viewers": 1161, "share_pct": 5.6}, {"rank": 4, "name": "TrU3Ta1ent", "viewers": 994, "share_pct": 4.8}, {"rank": 5, "name": "SwehYT", "viewers": 912, "share_pct": 4.4}, {"rank": 6, "name": "\u3089\u306b\u3063\u304f\u3059", "viewers": 788, "share_pct": 3.8}, {"rank": 7, "name": "Proxhy", "viewers": 421, "share_pct": 2.0}, {"rank": 8, "name": "Ghostkai", "viewers": 359, "share_pct": 1.7}, {"rank": 9, "name": "Swii", "viewers": 317, "share_pct": 1.5}], "Powerful Pro Yakyuu 2026-2027": [{"rank": 1, "name": "\u52a0\u85e4\u7d14\u4e00\u3046\u3093\u3007\u3061\u3083\u3093", "viewers": 21745, "share_pct": 99.5}, {"rank": 2, "name": "\u3046\u3069\u3093\u304a\u59c9\u3061\u3083\u3093", "viewers": 78, "share_pct": 0.4}, {"rank": 3, "name": "\u304b\u305a\u3061\u3083\u3093\u3060\u3088", "viewers": 15, "share_pct": 0.1}, {"rank": 4, "name": "\u79c1\u306f\u3060\u3044\u306a\u306a", "viewers": 12, "share_pct": 0.1}, {"rank": 5, "name": "\u30d5\u30af\u30c4", "viewers": 6, "share_pct": 0.0}, {"rank": 6, "name": "\u30b8\u30f3\u30d5\u30ea", "viewers": 5, "share_pct": 0.0}, {"rank": 7, "name": "kpch", "viewers": 4, "share_pct": 0.0}, {"rank": 8, "name": "\u3051\u3080116", "viewers": 4, "share_pct": 0.0}, {"rank": 9, "name": "\u307f\u304b\u3093\u3061\u3083\u3093\u306d\u308b0323", "viewers": 3, "share_pct": 0.0}, {"rank": 10, "name": "\u5730\u8535\u9662\u572d\u592a\u90ce\u307d\u3081\u3089\u3057", "viewers": 3, "share_pct": 0.0}], "MECCHA CHAMELEON": [{"rank": 1, "name": "Zerost_s", "viewers": 6067, "share_pct": 28.6}, {"rank": 2, "name": "yutapongo", "viewers": 3047, "share_pct": 14.3}, {"rank": 3, "name": "\u3057\u3083\u308b\u308b", "viewers": 1296, "share_pct": 6.1}, {"rank": 4, "name": "SgtGrafoyni", "viewers": 954, "share_pct": 4.5}, {"rank": 5, "name": "\u3068\u304a\u3053", "viewers": 585, "share_pct": 2.8}, {"rank": 6, "name": "AlphaAzur", "viewers": 554, "share_pct": 2.6}, {"rank": 7, "name": "\u5deb\u795e\u3053\u3093", "viewers": 521, "share_pct": 2.5}, {"rank": 8, "name": "\u3078\u3066\u308b", "viewers": 433, "share_pct": 2.0}, {"rank": 9, "name": "rafapacato", "viewers": 349, "share_pct": 1.6}, {"rank": 10, "name": "WOOM0N", "viewers": 337, "share_pct": 1.6}], "Diablo IV": [{"rank": 1, "name": "Rob2628", "viewers": 3785, "share_pct": 19.2}, {"rank": 2, "name": "wudijo", "viewers": 3262, "share_pct": 16.5}, {"rank": 3, "name": "pathofexilebota", "viewers": 1493, "share_pct": 7.6}, {"rank": 4, "name": "SlashingCreeps", "viewers": 833, "share_pct": 4.2}, {"rank": 5, "name": "JokerdTV", "viewers": 799, "share_pct": 4.1}, {"rank": 6, "name": "AuroralGames", "viewers": 669, "share_pct": 3.4}, {"rank": 7, "name": "P4wnyhof", "viewers": 654, "share_pct": 3.3}, {"rank": 8, "name": "Evangelion0", "viewers": 622, "share_pct": 3.2}, {"rank": 9, "name": "olszakumpel", "viewers": 621, "share_pct": 3.2}, {"rank": 10, "name": "Towelliee", "viewers": 491, "share_pct": 2.5}], "Shine Post: Be Your Idol!": [{"rank": 1, "name": "stylishnoob4", "viewers": 19470, "share_pct": 100.0}], "Hearthstone": [{"rank": 1, "name": "SuperJJ", "viewers": 1788, "share_pct": 10.5}, {"rank": 2, "name": "Cantelope", "viewers": 1744, "share_pct": 10.2}, {"rank": 3, "name": "SolaryHS", "viewers": 1343, "share_pct": 7.9}, {"rank": 4, "name": "\u859b\u559c", "viewers": 1219, "share_pct": 7.1}, {"rank": 5, "name": "RduLIVE", "viewers": 1095, "share_pct": 6.4}, {"rank": 6, "name": "aquabeamm", "viewers": 1093, "share_pct": 6.4}, {"rank": 7, "name": "\u856d\u653f\u9298", "viewers": 1080, "share_pct": 6.3}, {"rank": 8, "name": "matsuri_hs", "viewers": 1064, "share_pct": 6.2}, {"rank": 9, "name": "Shadybunny", "viewers": 694, "share_pct": 4.1}, {"rank": 10, "name": "Norwis_", "viewers": 594, "share_pct": 3.5}], "Fortnite": [{"rank": 1, "name": "Oatley", "viewers": 1461, "share_pct": 11.8}, {"rank": 2, "name": "Ache", "viewers": 1100, "share_pct": 8.9}, {"rank": 3, "name": "Recuerd0p", "viewers": 511, "share_pct": 4.1}, {"rank": 4, "name": "HappyHappyGal_VOD", "viewers": 341, "share_pct": 2.8}, {"rank": 5, "name": "OShakOnIG", "viewers": 303, "share_pct": 2.4}, {"rank": 6, "name": "Fasffy", "viewers": 295, "share_pct": 2.4}, {"rank": 7, "name": "Stizo_", "viewers": 295, "share_pct": 2.4}, {"rank": 8, "name": "HeartOfTheRegion", "viewers": 290, "share_pct": 2.3}, {"rank": 9, "name": "Mayucca", "viewers": 273, "share_pct": 2.2}], "Always On": [{"rank": 1, "name": "TheBurntPeanut_247", "viewers": 4396, "share_pct": 26.9}, {"rank": 2, "name": "gameplayboy22220", "viewers": 1425, "share_pct": 8.7}, {"rank": 3, "name": "Cohh", "viewers": 727, "share_pct": 4.4}, {"rank": 4, "name": "LacyOffline_", "viewers": 630, "share_pct": 3.8}, {"rank": 5, "name": "CineIlloJuan", "viewers": 534, "share_pct": 3.3}, {"rank": 6, "name": "ChilledChaos", "viewers": 527, "share_pct": 3.2}, {"rank": 7, "name": "LIRIK_247", "viewers": 434, "share_pct": 2.7}, {"rank": 8, "name": "AltairNative", "viewers": 394, "share_pct": 2.4}, {"rank": 9, "name": "shrood", "viewers": 377, "share_pct": 2.3}, {"rank": 10, "name": "RiffTrax", "viewers": 354, "share_pct": 2.2}], "Overwatch": [{"rank": 1, "name": "dafran", "viewers": 2708, "share_pct": 17.6}, {"rank": 2, "name": "iddqd", "viewers": 747, "share_pct": 4.9}, {"rank": 3, "name": "Winton_OW2", "viewers": 548, "share_pct": 3.6}, {"rank": 4, "name": "PLAYTO_ow", "viewers": 488, "share_pct": 3.2}, {"rank": 5, "name": "Kephrii", "viewers": 444, "share_pct": 2.9}, {"rank": 6, "name": "\u4ef2\u9054", "viewers": 417, "share_pct": 2.7}, {"rank": 7, "name": "sakurah", "viewers": 406, "share_pct": 2.6}, {"rank": 8, "name": "\u30d3\u30d3\u30f3\u30d0\u5c71\u672c", "viewers": 357, "share_pct": 2.3}, {"rank": 9, "name": "manda", "viewers": 300, "share_pct": 2.0}], "Genshin Impact": [{"rank": 1, "name": "\u61f6\u8c93", "viewers": 2263, "share_pct": 16.0}, {"rank": 2, "name": "\u5c0f\u70c8", "viewers": 1031, "share_pct": 7.3}, {"rank": 3, "name": "Sweetily", "viewers": 1009, "share_pct": 7.2}, {"rank": 4, "name": "\u306f\u308b\u3053\u3055\u3093", "viewers": 827, "share_pct": 5.9}, {"rank": 5, "name": "\u67da\u6728\u30ed\u30b3", "viewers": 746, "share_pct": 5.3}, {"rank": 6, "name": "Komemos", "viewers": 722, "share_pct": 5.1}, {"rank": 7, "name": "AsPig", "viewers": 620, "share_pct": 4.4}, {"rank": 8, "name": "Nokapt", "viewers": 520, "share_pct": 3.7}, {"rank": 9, "name": "Unsella", "viewers": 429, "share_pct": 3.0}, {"rank": 10, "name": "Sephijin", "viewers": 425, "share_pct": 3.0}], "World of Warcraft": [{"rank": 1, "name": "Guzu", "viewers": 1815, "share_pct": 12.9}, {"rank": 2, "name": "Ziqoftw", "viewers": 841, "share_pct": 6.0}, {"rank": 3, "name": "PsheroTV", "viewers": 670, "share_pct": 4.8}, {"rank": 4, "name": "kushlul", "viewers": 434, "share_pct": 3.1}, {"rank": 5, "name": "Sieglinde", "viewers": 397, "share_pct": 2.8}, {"rank": 6, "name": "Whaazz", "viewers": 362, "share_pct": 2.6}, {"rank": 7, "name": "Peettko", "viewers": 347, "share_pct": 2.5}, {"rank": 8, "name": "DilerTV", "viewers": 340, "share_pct": 2.4}, {"rank": 9, "name": "VodkaMage", "viewers": 313, "share_pct": 2.2}], "Tomodachi Life: Living the Dream": [{"rank": 1, "name": "fps_shaka", "viewers": 13424, "share_pct": 97.0}, {"rank": 2, "name": "pony0n", "viewers": 102, "share_pct": 0.7}, {"rank": 3, "name": "1FuGa", "viewers": 47, "share_pct": 0.3}, {"rank": 4, "name": "Mehluxka", "viewers": 43, "share_pct": 0.3}, {"rank": 5, "name": "JynnxeGaming", "viewers": 31, "share_pct": 0.2}, {"rank": 6, "name": "t_mikage", "viewers": 30, "share_pct": 0.2}, {"rank": 7, "name": "animanigma", "viewers": 22, "share_pct": 0.2}, {"rank": 8, "name": "sk_asriel", "viewers": 21, "share_pct": 0.2}, {"rank": 9, "name": "jai2go", "viewers": 16, "share_pct": 0.1}, {"rank": 10, "name": "AthemosVT", "viewers": 16, "share_pct": 0.1}], "Sports": [{"rank": 1, "name": "gerardromero", "viewers": 4586, "share_pct": 33.5}, {"rank": 2, "name": "BruceGrannec", "viewers": 2258, "share_pct": 16.5}, {"rank": 3, "name": "valentisanjuan", "viewers": 1523, "share_pct": 11.1}, {"rank": 4, "name": "ElChiringuitoTV", "viewers": 1244, "share_pct": 9.1}, {"rank": 5, "name": "LaGradaOnline", "viewers": 762, "share_pct": 5.6}, {"rank": 6, "name": "Juventibus", "viewers": 719, "share_pct": 5.3}, {"rank": 7, "name": "INAKIANGULOTV", "viewers": 698, "share_pct": 5.1}, {"rank": 8, "name": "FirstTeam101", "viewers": 468, "share_pct": 3.4}, {"rank": 9, "name": "teladoiotokyo", "viewers": 343, "share_pct": 2.5}, {"rank": 10, "name": "LaGrada914", "viewers": 237, "share_pct": 1.7}], "Rainbow Six Siege": [{"rank": 1, "name": "Rainbow6", "viewers": 5978, "share_pct": 56.1}, {"rank": 2, "name": "Rainbow6JP", "viewers": 804, "share_pct": 7.5}, {"rank": 3, "name": "Boggles", "viewers": 370, "share_pct": 3.5}, {"rank": 4, "name": "rasco100", "viewers": 215, "share_pct": 2.0}, {"rank": 5, "name": "FastAnne", "viewers": 160, "share_pct": 1.5}, {"rank": 6, "name": "Alicia", "viewers": 137, "share_pct": 1.3}, {"rank": 7, "name": "Skyte", "viewers": 128, "share_pct": 1.2}, {"rank": 8, "name": "vetelcito01", "viewers": 115, "share_pct": 1.1}, {"rank": 9, "name": "KingGeorgeOffline", "viewers": 92, "share_pct": 0.9}, {"rank": 10, "name": "\u306b\u3083\u306e\u3055\u307e", "viewers": 84, "share_pct": 0.8}], "Virtual Casino": [{"rank": 1, "name": "PoqeFob7", "viewers": 2010, "share_pct": 18.2}, {"rank": 2, "name": "Nokan777", "viewers": 1362, "share_pct": 12.4}, {"rank": 3, "name": "SintoniaDaSorte", "viewers": 1042, "share_pct": 9.5}, {"rank": 4, "name": "gu_strike", "viewers": 971, "share_pct": 8.8}, {"rank": 5, "name": "Hudsonabr1", "viewers": 905, "share_pct": 8.2}, {"rank": 6, "name": "ifnonadish", "viewers": 559, "share_pct": 5.1}, {"rank": 7, "name": "tuydoha", "viewers": 547, "share_pct": 5.0}, {"rank": 8, "name": "wildis_sous", "viewers": 540, "share_pct": 4.9}, {"rank": 9, "name": "tsayokoclub", "viewers": 533, "share_pct": 4.8}, {"rank": 10, "name": "ramz3iro", "viewers": 525, "share_pct": 4.8}], "Escape from Tarkov": [{"rank": 1, "name": "Glorious_E", "viewers": 3036, "share_pct": 32.5}, {"rank": 2, "name": "AIMLUL", "viewers": 1409, "share_pct": 15.1}, {"rank": 3, "name": "\u3068\u3068\u307f\u3063\u304f\u3059", "viewers": 1023, "share_pct": 11.0}, {"rank": 4, "name": "2TwistedTV", "viewers": 602, "share_pct": 6.5}, {"rank": 5, "name": "dahmien7", "viewers": 350, "share_pct": 3.8}, {"rank": 6, "name": "sadpocky", "viewers": 339, "share_pct": 3.6}, {"rank": 7, "name": "knueppelpaste", "viewers": 301, "share_pct": 3.2}, {"rank": 8, "name": "VeryBadSCAV", "viewers": 227, "share_pct": 2.4}, {"rank": 9, "name": "GgSanTomE", "viewers": 174, "share_pct": 1.9}, {"rank": 10, "name": "\u82b1\u82bd\u5c0b\u304b\u3059\u307f", "viewers": 145, "share_pct": 1.6}], "Arena Breakout: Infinite": [{"rank": 1, "name": "ImOw", "viewers": 2317, "share_pct": 22.8}, {"rank": 2, "name": "QuattroAce", "viewers": 1468, "share_pct": 14.5}, {"rank": 3, "name": "samoylov___", "viewers": 1076, "share_pct": 10.6}, {"rank": 4, "name": "HALFLEX", "viewers": 987, "share_pct": 9.7}, {"rank": 5, "name": "SuraFPS", "viewers": 420, "share_pct": 4.1}, {"rank": 6, "name": "kassshiro", "viewers": 280, "share_pct": 2.8}, {"rank": 7, "name": "Buggy", "viewers": 236, "share_pct": 2.3}, {"rank": 8, "name": "DUSSHNILA", "viewers": 203, "share_pct": 2.0}, {"rank": 9, "name": "Miniuwa", "viewers": 142, "share_pct": 1.4}, {"rank": 10, "name": "DISTRUCT_STREAM", "viewers": 136, "share_pct": 1.3}], "Path of Exile 2": [{"rank": 1, "name": "Zizaran", "viewers": 1547, "share_pct": 15.4}, {"rank": 2, "name": "madarapoe", "viewers": 1295, "share_pct": 12.9}, {"rank": 3, "name": "DEADRABB1T", "viewers": 889, "share_pct": 8.8}, {"rank": 4, "name": "Steelmage", "viewers": 674, "share_pct": 6.7}, {"rank": 5, "name": "iLame", "viewers": 631, "share_pct": 6.3}, {"rank": 6, "name": "Takluz", "viewers": 603, "share_pct": 6.0}, {"rank": 7, "name": "redviles", "viewers": 580, "share_pct": 5.8}, {"rank": 8, "name": "\u60e1\u9b54\u8c93\u8c93\u8c93", "viewers": 373, "share_pct": 3.7}, {"rank": 9, "name": "MisoxShiru", "viewers": 349, "share_pct": 3.5}, {"rank": 10, "name": "terence_", "viewers": 245, "share_pct": 2.4}], "Minecraft": [{"rank": 1, "name": "Boosfer", "viewers": 371, "share_pct": 4.7}, {"rank": 2, "name": "AiroKun", "viewers": 367, "share_pct": 4.6}, {"rank": 3, "name": "Dimeax", "viewers": 261, "share_pct": 3.3}, {"rank": 4, "name": "LilyMaiDarling", "viewers": 248, "share_pct": 3.1}, {"rank": 5, "name": "KingIvanTheEpic", "viewers": 209, "share_pct": 2.6}, {"rank": 6, "name": "BarsiGold", "viewers": 202, "share_pct": 2.5}, {"rank": 7, "name": "JonahBirch", "viewers": 194, "share_pct": 2.4}, {"rank": 8, "name": "nater4L", "viewers": 161, "share_pct": 2.0}, {"rank": 9, "name": "Jozukai", "viewers": 148, "share_pct": 1.9}], "Call of Duty: Warzone": [{"rank": 1, "name": "Zyro", "viewers": 869, "share_pct": 9.8}, {"rank": 2, "name": "STYLERZ", "viewers": 609, "share_pct": 6.9}, {"rank": 3, "name": "exely", "viewers": 457, "share_pct": 5.2}, {"rank": 4, "name": "ESKc", "viewers": 449, "share_pct": 5.1}, {"rank": 5, "name": "etokeking", "viewers": 333, "share_pct": 3.8}, {"rank": 6, "name": "bigdaddygmann", "viewers": 330, "share_pct": 3.7}, {"rank": 7, "name": "LanoCallum1", "viewers": 299, "share_pct": 3.4}, {"rank": 8, "name": "BennyCentral", "viewers": 225, "share_pct": 2.5}, {"rank": 9, "name": "AaronTheLoco", "viewers": 218, "share_pct": 2.5}], "7 Days to Die": [{"rank": 1, "name": "\u305f\u3044\u3058_\u305f\u3044\u3061\u3083\u3093\u306d\u308b", "viewers": 7766, "share_pct": 87.9}, {"rank": 2, "name": "Hard_Survival", "viewers": 162, "share_pct": 1.8}, {"rank": 3, "name": "Frantic_Dan", "viewers": 114, "share_pct": 1.3}, {"rank": 4, "name": "OtterLady", "viewers": 113, "share_pct": 1.3}, {"rank": 5, "name": "DD1GG", "viewers": 103, "share_pct": 1.2}, {"rank": 6, "name": "AsmodisdeSanktis", "viewers": 65, "share_pct": 0.7}, {"rank": 7, "name": "HonigZitrone", "viewers": 58, "share_pct": 0.7}, {"rank": 8, "name": "Qb1Junkie", "viewers": 40, "share_pct": 0.5}, {"rank": 9, "name": "\u767d\u9280\u30b7\u30d0", "viewers": 33, "share_pct": 0.4}, {"rank": 10, "name": "yaseithefox", "viewers": 32, "share_pct": 0.4}], "Slots": [{"rank": 1, "name": "KytuGyku48", "viewers": 1950, "share_pct": 22.4}, {"rank": 2, "name": "KajiTepe", "viewers": 1310, "share_pct": 15.1}, {"rank": 3, "name": "Bonustrio", "viewers": 679, "share_pct": 7.8}, {"rank": 4, "name": "CasinoDaddy", "viewers": 653, "share_pct": 7.5}, {"rank": 5, "name": "gigicasper", "viewers": 472, "share_pct": 5.4}, {"rank": 6, "name": "orangemorangeSlots", "viewers": 285, "share_pct": 3.3}, {"rank": 7, "name": "gTastySlots", "viewers": 269, "share_pct": 3.1}, {"rank": 8, "name": "maxpainslots", "viewers": 242, "share_pct": 2.8}, {"rank": 9, "name": "onlywindeslots", "viewers": 242, "share_pct": 2.8}, {"rank": 10, "name": "slotshub_skillz", "viewers": 233, "share_pct": 2.7}], "Marvel Rivals": [{"rank": 1, "name": "kragiee", "viewers": 994, "share_pct": 13.1}, {"rank": 2, "name": "PIZZADEMON", "viewers": 576, "share_pct": 7.6}, {"rank": 3, "name": "Woofles", "viewers": 451, "share_pct": 5.9}, {"rank": 4, "name": "zazzastack", "viewers": 410, "share_pct": 5.4}, {"rank": 5, "name": "whyAndr3w", "viewers": 266, "share_pct": 3.5}, {"rank": 6, "name": "Annanutaa", "viewers": 205, "share_pct": 2.7}, {"rank": 7, "name": "snakeCase2", "viewers": 173, "share_pct": 2.3}, {"rank": 8, "name": "cichwiz", "viewers": 170, "share_pct": 2.2}, {"rank": 9, "name": "RVOTAENOTA", "viewers": 148, "share_pct": 1.9}, {"rank": 10, "name": "Eshego", "viewers": 142, "share_pct": 1.9}], "Art": [{"rank": 1, "name": "DyaRikku", "viewers": 860, "share_pct": 10.7}, {"rank": 2, "name": "\u30e2\u8ab0", "viewers": 440, "share_pct": 5.5}, {"rank": 3, "name": "symon_redd", "viewers": 186, "share_pct": 2.3}, {"rank": 4, "name": "nanaaachan", "viewers": 148, "share_pct": 1.8}, {"rank": 5, "name": "IchiraArt", "viewers": 136, "share_pct": 1.7}, {"rank": 6, "name": "Tirumisa", "viewers": 125, "share_pct": 1.6}, {"rank": 7, "name": "TINY_AIRY", "viewers": 116, "share_pct": 1.4}, {"rank": 8, "name": "\u963f\u6817_", "viewers": 108, "share_pct": 1.3}, {"rank": 9, "name": "charlyn", "viewers": 106, "share_pct": 1.3}, {"rank": 10, "name": "ComfyPeachh", "viewers": 99, "share_pct": 1.2}], "Old School RuneScape": [{"rank": 1, "name": "B0aty", "viewers": 2644, "share_pct": 32.7}, {"rank": 2, "name": "Skiddler", "viewers": 1153, "share_pct": 14.3}, {"rank": 3, "name": "Mmorpg", "viewers": 596, "share_pct": 7.4}, {"rank": 4, "name": "EvScape", "viewers": 532, "share_pct": 6.6}, {"rank": 5, "name": "SkillSpecs", "viewers": 470, "share_pct": 5.8}, {"rank": 6, "name": "jillyfish", "viewers": 359, "share_pct": 4.4}, {"rank": 7, "name": "Soy_Duro", "viewers": 238, "share_pct": 2.9}, {"rank": 8, "name": "Widega_", "viewers": 229, "share_pct": 2.8}, {"rank": 9, "name": "domas_osrs", "viewers": 212, "share_pct": 2.6}, {"rank": 10, "name": "Katerena", "viewers": 187, "share_pct": 2.3}], "Street Fighter 6": [{"rank": 1, "name": "\u767d\u6ce2\u3089\u3080\u306d", "viewers": 2788, "share_pct": 37.6}, {"rank": 2, "name": "\u306a\u308b\u304a_", "viewers": 1069, "share_pct": 14.4}, {"rank": 3, "name": "\u7acb\u5ddd", "viewers": 956, "share_pct": 12.9}, {"rank": 4, "name": "\u751f\u99d2\u3069\u3050\u3089\u30c7\u30d3\u30eb", "viewers": 887, "share_pct": 11.9}, {"rank": 5, "name": "\u308d\u305c\u3063\u304f\u3074\u3093", "viewers": 521, "share_pct": 7.0}, {"rank": 6, "name": "yoro1027", "viewers": 127, "share_pct": 1.7}, {"rank": 7, "name": "\u60a0\u6728\u3061\u306f\u3084", "viewers": 110, "share_pct": 1.5}, {"rank": 8, "name": "karura_sf", "viewers": 102, "share_pct": 1.4}, {"rank": 9, "name": "\u306a\u304b\u3042\u3057", "viewers": 99, "share_pct": 1.3}, {"rank": 10, "name": "SFAustralia", "viewers": 69, "share_pct": 0.9}], "Delta Force": [{"rank": 1, "name": "off_kuka358", "viewers": 2419, "share_pct": 34.7}, {"rank": 2, "name": "EqualPlays", "viewers": 523, "share_pct": 7.5}, {"rank": 3, "name": "ALEKSANDRsttv", "viewers": 317, "share_pct": 4.6}, {"rank": 4, "name": "stikinson", "viewers": 235, "share_pct": 3.4}, {"rank": 5, "name": "Drewd0g", "viewers": 202, "share_pct": 2.9}, {"rank": 6, "name": "cook_playing", "viewers": 178, "share_pct": 2.6}, {"rank": 7, "name": "ReDDuch", "viewers": 149, "share_pct": 2.1}, {"rank": 8, "name": "NokSs68", "viewers": 145, "share_pct": 2.1}, {"rank": 9, "name": "siingsong", "viewers": 136, "share_pct": 2.0}, {"rank": 10, "name": "\u4f55\u8001\u5e2b", "viewers": 115, "share_pct": 1.7}], "Sand: Raiders Of Sophie": [{"rank": 1, "name": "\u72c2\u66b4\u5c0f\u5efa", "viewers": 1015, "share_pct": 14.0}, {"rank": 2, "name": "Ceremor", "viewers": 810, "share_pct": 11.2}, {"rank": 3, "name": "Moonryde", "viewers": 800, "share_pct": 11.0}, {"rank": 4, "name": "\u674f\u4ec1\u30df\u30eb", "viewers": 689, "share_pct": 9.5}, {"rank": 5, "name": "PROD", "viewers": 609, "share_pct": 8.4}, {"rank": 6, "name": "Dezignful", "viewers": 430, "share_pct": 5.9}, {"rank": 7, "name": "TORRO", "viewers": 426, "share_pct": 5.9}, {"rank": 8, "name": "trausi", "viewers": 282, "share_pct": 3.9}, {"rank": 9, "name": "slumbo_", "viewers": 255, "share_pct": 3.5}, {"rank": 10, "name": "\u8001\u5339", "viewers": 206, "share_pct": 2.8}], "ASMR": [{"rank": 1, "name": "mewreci", "viewers": 1642, "share_pct": 26.2}, {"rank": 2, "name": "TheNicoleT", "viewers": 699, "share_pct": 11.2}, {"rank": 3, "name": "Lovella", "viewers": 515, "share_pct": 8.2}, {"rank": 4, "name": "Neriaenn", "viewers": 304, "share_pct": 4.9}, {"rank": 5, "name": "MireiaBesi", "viewers": 262, "share_pct": 4.2}, {"rank": 6, "name": "SharonQueen", "viewers": 208, "share_pct": 3.3}, {"rank": 7, "name": "KaileyMaeASMR", "viewers": 195, "share_pct": 3.1}, {"rank": 8, "name": "ivyheals", "viewers": 189, "share_pct": 3.0}, {"rank": 9, "name": "Tingting57", "viewers": 142, "share_pct": 2.3}, {"rank": 10, "name": "moridesuu_", "viewers": 134, "share_pct": 2.1}], "I'm Only Sleeping": [{"rank": 1, "name": "Dantes", "viewers": 1886, "share_pct": 32.9}, {"rank": 2, "name": "JaguarN1", "viewers": 355, "share_pct": 6.2}, {"rank": 3, "name": "Leopard", "viewers": 286, "share_pct": 5.0}, {"rank": 4, "name": "Bondarenk01", "viewers": 253, "share_pct": 4.4}, {"rank": 5, "name": "necronival", "viewers": 237, "share_pct": 4.1}, {"rank": 6, "name": "coreydarbo", "viewers": 160, "share_pct": 2.8}, {"rank": 7, "name": "Yuumine", "viewers": 149, "share_pct": 2.6}, {"rank": 8, "name": "jorge", "viewers": 142, "share_pct": 2.5}, {"rank": 9, "name": "XISTERAfps", "viewers": 140, "share_pct": 2.4}, {"rank": 10, "name": "ShizzyDE", "viewers": 119, "share_pct": 2.1}], "PUBG: BATTLEGROUNDS": [{"rank": 1, "name": "Cucu0015", "viewers": 461, "share_pct": 9.2}, {"rank": 2, "name": "J0niQ", "viewers": 307, "share_pct": 6.1}, {"rank": 3, "name": "zuluxxman", "viewers": 306, "share_pct": 6.1}, {"rank": 4, "name": "chiawei1031tv", "viewers": 301, "share_pct": 6.0}, {"rank": 5, "name": "PUBGThailandOfficial", "viewers": 283, "share_pct": 5.6}, {"rank": 6, "name": "bLYYYPLAYS", "viewers": 249, "share_pct": 5.0}, {"rank": 7, "name": "Antony_Gamer", "viewers": 203, "share_pct": 4.1}, {"rank": 8, "name": "jeemzz", "viewers": 202, "share_pct": 4.0}, {"rank": 9, "name": "Skrolya", "viewers": 160, "share_pct": 3.2}, {"rank": 10, "name": "OfficialAndyPyro", "viewers": 151, "share_pct": 3.0}], "ARC Raiders": [{"rank": 1, "name": "LEV_BRITVAAA", "viewers": 689, "share_pct": 14.8}, {"rank": 2, "name": "ShinyaTheNinja", "viewers": 504, "share_pct": 10.8}, {"rank": 3, "name": "EnlightenedGamerX", "viewers": 458, "share_pct": 9.8}, {"rank": 4, "name": "lyesval", "viewers": 373, "share_pct": 8.0}, {"rank": 5, "name": "xNikGo", "viewers": 363, "share_pct": 7.8}, {"rank": 6, "name": "JSavageW", "viewers": 345, "share_pct": 7.4}, {"rank": 7, "name": "FreeSuave", "viewers": 160, "share_pct": 3.4}, {"rank": 8, "name": "MARVIN", "viewers": 101, "share_pct": 2.2}, {"rank": 9, "name": "Phixate", "viewers": 98, "share_pct": 2.1}, {"rank": 10, "name": "Elpapitank", "viewers": 72, "share_pct": 1.5}], "Music": [{"rank": 1, "name": "LavieEdenel", "viewers": 1250, "share_pct": 30.5}, {"rank": 2, "name": "WindowlightFM", "viewers": 229, "share_pct": 5.6}, {"rank": 3, "name": "filiplackovicmusic", "viewers": 213, "share_pct": 5.2}, {"rank": 4, "name": "LofiMusic3232", "viewers": 137, "share_pct": 3.3}, {"rank": 5, "name": "sayanoe", "viewers": 136, "share_pct": 3.3}, {"rank": 6, "name": "jadebaquiano", "viewers": 112, "share_pct": 2.7}, {"rank": 7, "name": "LofiGirl", "viewers": 110, "share_pct": 2.7}, {"rank": 8, "name": "RelaxBeats", "viewers": 105, "share_pct": 2.6}], "Resident Evil 4": [{"rank": 1, "name": "SamoAgo", "viewers": 2240, "share_pct": 50.7}, {"rank": 2, "name": "Trickywi", "viewers": 1923, "share_pct": 43.5}, {"rank": 3, "name": "LeaDNLZ", "viewers": 94, "share_pct": 2.1}, {"rank": 4, "name": "Aaiza_Project", "viewers": 62, "share_pct": 1.4}, {"rank": 5, "name": "\u3042\u30848", "viewers": 26, "share_pct": 0.6}, {"rank": 6, "name": "LittleMissNZ", "viewers": 18, "share_pct": 0.4}, {"rank": 7, "name": "\u5287\u4f5c\u5bb6\u306e\u3057\u3052\u306e\u3076\u3067\u3059", "viewers": 16, "share_pct": 0.4}, {"rank": 8, "name": "hornedpogasus", "viewers": 11, "share_pct": 0.2}, {"rank": 9, "name": "ParioGames", "viewers": 9, "share_pct": 0.2}, {"rank": 10, "name": "NutaOo", "viewers": 8, "share_pct": 0.2}], "World of Tanks": [{"rank": 1, "name": "Orzanel", "viewers": 1615, "share_pct": 36.8}, {"rank": 2, "name": "Killer0005_", "viewers": 331, "share_pct": 7.5}, {"rank": 3, "name": "AwesomeEpicGuys", "viewers": 215, "share_pct": 4.9}, {"rank": 4, "name": "Fr3ddy_TV", "viewers": 205, "share_pct": 4.7}, {"rank": 5, "name": "Benso", "viewers": 163, "share_pct": 3.7}, {"rank": 6, "name": "DraVz_", "viewers": 163, "share_pct": 3.7}, {"rank": 7, "name": "samiyka", "viewers": 162, "share_pct": 3.7}, {"rank": 8, "name": "FC_DYNAMO", "viewers": 148, "share_pct": 3.4}, {"rank": 9, "name": "giianiinaa98", "viewers": 109, "share_pct": 2.5}, {"rank": 10, "name": "Roha_wot", "viewers": 99, "share_pct": 2.3}], "Football Manager 26": [{"rank": 1, "name": "Dmitry_Lixxx", "viewers": 4346, "share_pct": 94.4}, {"rank": 2, "name": "BadeschlappenLP", "viewers": 148, "share_pct": 3.2}, {"rank": 3, "name": "Ticker147", "viewers": 62, "share_pct": 1.3}, {"rank": 4, "name": "levosgienenbretagnelive", "viewers": 14, "share_pct": 0.3}, {"rank": 5, "name": "ConstantlyChris_", "viewers": 11, "share_pct": 0.2}, {"rank": 6, "name": "TheWelshFootballManager", "viewers": 10, "share_pct": 0.2}, {"rank": 7, "name": "freecelltv", "viewers": 6, "share_pct": 0.1}, {"rank": 8, "name": "ejszwagier", "viewers": 5, "share_pct": 0.1}, {"rank": 9, "name": "JORDYPGK", "viewers": 4, "share_pct": 0.1}, {"rank": 10, "name": "Skillzamba", "viewers": 4, "share_pct": 0.1}], "Warframe": [{"rank": 1, "name": "NeoNess007", "viewers": 1496, "share_pct": 35.8}, {"rank": 2, "name": "Pupsker", "viewers": 363, "share_pct": 8.7}, {"rank": 3, "name": "LeyzarGamingViews", "viewers": 253, "share_pct": 6.1}, {"rank": 4, "name": "Leamxp", "viewers": 214, "share_pct": 5.1}, {"rank": 5, "name": "BryceBreaks", "viewers": 128, "share_pct": 3.1}, {"rank": 6, "name": "ApolRei", "viewers": 117, "share_pct": 2.8}, {"rank": 7, "name": "xROSEBUDo", "viewers": 107, "share_pct": 2.6}, {"rank": 8, "name": "TheEmernyx", "viewers": 105, "share_pct": 2.5}, {"rank": 9, "name": "Backyardis", "viewers": 105, "share_pct": 2.5}, {"rank": 10, "name": "Kyrielle", "viewers": 99, "share_pct": 2.4}], "DayZ": [{"rank": 1, "name": "Smoke", "viewers": 2424, "share_pct": 56.8}, {"rank": 2, "name": "Brizereins", "viewers": 206, "share_pct": 4.8}, {"rank": 3, "name": "slexify", "viewers": 196, "share_pct": 4.6}, {"rank": 4, "name": "Pandowner", "viewers": 190, "share_pct": 4.5}, {"rank": 5, "name": "FubarBundy", "viewers": 130, "share_pct": 3.0}, {"rank": 6, "name": "Sunday", "viewers": 126, "share_pct": 3.0}, {"rank": 7, "name": "DemZ", "viewers": 96, "share_pct": 2.2}, {"rank": 8, "name": "Amacky", "viewers": 69, "share_pct": 1.6}, {"rank": 9, "name": "kromkachleba", "viewers": 69, "share_pct": 1.6}, {"rank": 10, "name": "Ayooooz ", "viewers": 58, "share_pct": 1.4}], "EA Sports FC 26": [{"rank": 1, "name": "Stokes", "viewers": 1207, "share_pct": 30.5}, {"rank": 2, "name": "xpazzoo", "viewers": 502, "share_pct": 12.7}, {"rank": 3, "name": "MaatM", "viewers": 186, "share_pct": 4.7}, {"rank": 4, "name": "RiberaRibell", "viewers": 151, "share_pct": 3.8}, {"rank": 5, "name": "miguez01", "viewers": 136, "share_pct": 3.4}, {"rank": 6, "name": "eadriaticleague01", "viewers": 124, "share_pct": 3.1}, {"rank": 7, "name": "eadriaticleaguetwo", "viewers": 116, "share_pct": 2.9}, {"rank": 8, "name": "Fritay1", "viewers": 104, "share_pct": 2.6}, {"rank": 9, "name": "JoshRyder", "viewers": 91, "share_pct": 2.3}, {"rank": 10, "name": "JohnFutUniverse", "viewers": 76, "share_pct": 1.9}], "Deadlock": [{"rank": 1, "name": "AverageJonas", "viewers": 1077, "share_pct": 26.0}, {"rank": 2, "name": "TheS1tuation", "viewers": 576, "share_pct": 13.9}, {"rank": 3, "name": "Xera", "viewers": 324, "share_pct": 7.8}, {"rank": 4, "name": "pkmk", "viewers": 293, "share_pct": 7.1}, {"rank": 5, "name": "fargareko", "viewers": 284, "share_pct": 6.8}, {"rank": 6, "name": "basildl", "viewers": 183, "share_pct": 4.4}, {"rank": 7, "name": "FanTIKKing", "viewers": 126, "share_pct": 3.0}, {"rank": 8, "name": "sangha82", "viewers": 115, "share_pct": 2.8}, {"rank": 9, "name": "AdamFromAus", "viewers": 111, "share_pct": 2.7}, {"rank": 10, "name": "fatcuk", "viewers": 87, "share_pct": 2.1}], "Mobile Legends: Bang Bang": [{"rank": 1, "name": "MLBB_CIS", "viewers": 1689, "share_pct": 40.7}, {"rank": 2, "name": "betboom_esports", "viewers": 458, "share_pct": 11.0}, {"rank": 3, "name": "nagibml", "viewers": 289, "share_pct": 7.0}, {"rank": 4, "name": "infinityvem", "viewers": 244, "share_pct": 5.9}, {"rank": 5, "name": "disowned_mlbb", "viewers": 229, "share_pct": 5.5}, {"rank": 6, "name": "ScottyKil", "viewers": 209, "share_pct": 5.0}, {"rank": 7, "name": "lensikc", "viewers": 180, "share_pct": 4.3}, {"rank": 8, "name": "strykermlbb", "viewers": 118, "share_pct": 2.8}, {"rank": 9, "name": "lckclchallengersleague", "viewers": 77, "share_pct": 1.9}, {"rank": 10, "name": "missclickqt", "viewers": 71, "share_pct": 1.7}]}}