{"generated_at": "2026-07-07T11:00:50.094917+00:00", "latest_snapshot": "2026-07-07T12:00:04.000775+01:00", "previous": {"snapshot": "2026-07-07T09:00:03.904531+01:00", "total": 493576, "by_category": {"Just Chatting": 111053, "League of Legends": 47302, "VALORANT": 33995, "IRL": 28283, "Star Wars: Jedi Knight - Dark Forces II": 27926, "ELDEN RING NIGHTREIGN": 26520, "Grand Theft Auto V": 23949, "Counter-Strike": 21521, "Dota 2": 22823, "Dead by Daylight": 17711, "Fortnite": 13736, "Marvel Rivals": 15372, "Overwatch": 15569, "Apex Legends": 14976, "Always On": 15060, "ROBLOX": 13411, "Assassin's Creed Black Flag Resynced": 11816, "Rust": 10932, "ASMR": 11034, "Sand: Raiders Of Sophie": 10587}}, "current": [{"category": "Just Chatting", "rank": 1, "viewership": 137469, "top10_pct": 21.1}, {"category": "VALORANT", "rank": 2, "viewership": 110008, "top10_pct": 79.2}, {"category": "Dota 2", "rank": 3, "viewership": 89375, "top10_pct": 69.9}, {"category": "Apex Legends", "rank": 4, "viewership": 70514, "top10_pct": 80.8}, {"category": "League of Legends", "rank": 5, "viewership": 62477, "top10_pct": 30.5}, {"category": "Rust", "rank": 6, "viewership": 52452, "top10_pct": 95.4}, {"category": "Counter-Strike", "rank": 7, "viewership": 33633, "top10_pct": 46.0}, {"category": "IRL", "rank": 8, "viewership": 30161, "top10_pct": 48.5}, {"category": "Grand Theft Auto V", "rank": 9, "viewership": 18990, "top10_pct": 29.3}, {"category": "World of Warcraft", "rank": 10, "viewership": 20270, "top10_pct": 47.9}, {"category": "Fortnite", "rank": 11, "viewership": 16062, "top10_pct": 61.4}, {"category": "Dead by Daylight", "rank": 12, "viewership": 17285, "top10_pct": 37.7}, {"category": "ELDEN RING NIGHTREIGN", "rank": 13, "viewership": 17302, "top10_pct": 98.1}, {"category": "Sparkster", "rank": 14, "viewership": 0, "top10_pct": null}, {"category": "Always On", "rank": 15, "viewership": 15222, "top10_pct": 48.4}, {"category": "Sports", "rank": 16, "viewership": 15400, "top10_pct": 91.9}, {"category": "Overwatch", "rank": 17, "viewership": 10984, "top10_pct": 47.1}, {"category": "Marvel Rivals", "rank": 18, "viewership": 13074, "top10_pct": 58.2}, {"category": "Hearthstone", "rank": 19, "viewership": 12438, "top10_pct": 71.8}, {"category": "Escape from Tarkov", "rank": 20, "viewership": 11426, "top10_pct": 78.0}], "streamers": {"Just Chatting": [{"rank": 1, "name": "Dracon", "viewers": 4038, "share_pct": 2.9}, {"rank": 2, "name": "robcdee", "viewers": 3714, "share_pct": 2.7}, {"rank": 3, "name": "rostikfacekid", "viewers": 3405, "share_pct": 2.5}, {"rank": 4, "name": "\u7d0b\u7d0b__", "viewers": 3198, "share_pct": 2.3}, {"rank": 5, "name": "WHOPLOHOYPAREN", "viewers": 2820, "share_pct": 2.1}, {"rank": 6, "name": "whylollycry", "viewers": 2649, "share_pct": 1.9}, {"rank": 7, "name": "viggomagiccc", "viewers": 2609, "share_pct": 1.9}, {"rank": 8, "name": "xKamysh", "viewers": 2437, "share_pct": 1.8}, {"rank": 9, "name": "\u8766\u611b\u6a58\u5b50", "viewers": 2068, "share_pct": 1.5}, {"rank": 10, "name": "LOTA", "viewers": 2026, "share_pct": 1.5}], "VALORANT": [{"rank": 1, "name": "Inoxtag", "viewers": 61638, "share_pct": 56.0}, {"rank": 2, "name": "gon_vl", "viewers": 12376, "share_pct": 11.3}, {"rank": 3, "name": "Lazvell", "viewers": 4105, "share_pct": 3.7}, {"rank": 4, "name": "EWC_stcArena_EN", "viewers": 2257, "share_pct": 2.1}, {"rank": 5, "name": "SuperBusS_", "viewers": 1916, "share_pct": 1.7}, {"rank": 6, "name": "foxzfoxzfoxz", "viewers": 1205, "share_pct": 1.1}, {"rank": 7, "name": "VALORANT_Pacific", "viewers": 1097, "share_pct": 1.0}, {"rank": 8, "name": "Grimm", "viewers": 965, "share_pct": 0.9}, {"rank": 9, "name": "DETHSEIYA", "viewers": 810, "share_pct": 0.7}, {"rank": 10, "name": "cloudey", "viewers": 736, "share_pct": 0.7}], "Dota 2": [{"rank": 1, "name": "Solo", "viewers": 20974, "share_pct": 23.5}, {"rank": 2, "name": "betboom_dota_ru", "viewers": 11252, "share_pct": 12.6}, {"rank": 3, "name": "dyrachyo", "viewers": 6004, "share_pct": 6.7}, {"rank": 4, "name": "EWC_LegionGauntlet_EN", "viewers": 5625, "share_pct": 6.3}, {"rank": 5, "name": "Koma", "viewers": 4988, "share_pct": 5.6}, {"rank": 6, "name": "Gorgc", "viewers": 4715, "share_pct": 5.3}, {"rank": 7, "name": "Arteezy", "viewers": 2862, "share_pct": 3.2}, {"rank": 8, "name": "Daxak", "viewers": 2831, "share_pct": 3.2}, {"rank": 9, "name": "blindzonexgod", "viewers": 1792, "share_pct": 2.0}, {"rank": 10, "name": "TORONTOTOKYO17", "viewers": 1412, "share_pct": 1.6}], "Apex Legends": [{"rank": 1, "name": "playapex", "viewers": 15190, "share_pct": 21.5}, {"rank": 2, "name": "esports_rage", "viewers": 10852, "share_pct": 15.4}, {"rank": 3, "name": "NiceWigg", "viewers": 8425, "share_pct": 11.9}, {"rank": 4, "name": "restiafps", "viewers": 5145, "share_pct": 7.3}, {"rank": 5, "name": "\u570b\u6fe4", "viewers": 5119, "share_pct": 7.3}, {"rank": 6, "name": "\u3086\u304d\u304a2", "viewers": 4791, "share_pct": 6.8}, {"rank": 7, "name": "Mande", "viewers": 3338, "share_pct": 4.7}, {"rank": 8, "name": "9impulse", "viewers": 1852, "share_pct": 2.6}, {"rank": 9, "name": "algs1_team12", "viewers": 1623, "share_pct": 2.3}, {"rank": 10, "name": "\u3042\u3063\u3057\u30fc", "viewers": 631, "share_pct": 0.9}], "League of Legends": [{"rank": 1, "name": "\u4e16\u8aa0", "viewers": 3474, "share_pct": 5.6}, {"rank": 2, "name": "Broxah", "viewers": 3205, "share_pct": 5.1}, {"rank": 3, "name": "Sardoche", "viewers": 2385, "share_pct": 3.8}, {"rank": 4, "name": "NiteNightKid", "viewers": 1551, "share_pct": 2.5}, {"rank": 5, "name": "agurin", "viewers": 1486, "share_pct": 2.4}, {"rank": 6, "name": "crownie_lol", "viewers": 1481, "share_pct": 2.4}, {"rank": 7, "name": "midbeast", "viewers": 1457, "share_pct": 2.3}, {"rank": 8, "name": "Lourlo", "viewers": 1414, "share_pct": 2.3}, {"rank": 9, "name": "GoBGG", "viewers": 1362, "share_pct": 2.2}, {"rank": 10, "name": "Overpow", "viewers": 1247, "share_pct": 2.0}], "Rust": [{"rank": 1, "name": "\u52a0\u85e4\u7d14\u4e00\u3046\u3093\u3007\u3061\u3083\u3093", "viewers": 44165, "share_pct": 84.2}, {"rank": 2, "name": "Oilrats", "viewers": 3185, "share_pct": 6.1}, {"rank": 3, "name": "Krolay", "viewers": 637, "share_pct": 1.2}, {"rank": 4, "name": "\u8ecd\u5e2b\u30df\u30ce\u30eb", "viewers": 521, "share_pct": 1.0}, {"rank": 5, "name": "Myko", "viewers": 320, "share_pct": 0.6}, {"rank": 6, "name": "mrsplinter_tv", "viewers": 272, "share_pct": 0.5}, {"rank": 7, "name": "Junin", "viewers": 254, "share_pct": 0.5}, {"rank": 8, "name": "snowmers", "viewers": 249, "share_pct": 0.5}, {"rank": 9, "name": "meksikanec74", "viewers": 218, "share_pct": 0.4}, {"rank": 10, "name": "vitollo_13", "viewers": 200, "share_pct": 0.4}], "Counter-Strike": [{"rank": 1, "name": "m3wsu", "viewers": 3939, "share_pct": 11.7}, {"rank": 2, "name": "chopperinho", "viewers": 2256, "share_pct": 6.7}, {"rank": 3, "name": "szelioficjalnie", "viewers": 1630, "share_pct": 4.8}, {"rank": 4, "name": "olofmeister", "viewers": 1580, "share_pct": 4.7}, {"rank": 5, "name": "renyan", "viewers": 1278, "share_pct": 3.8}, {"rank": 6, "name": "f0rest", "viewers": 1102, "share_pct": 3.3}, {"rank": 7, "name": "zonixxcs", "viewers": 1004, "share_pct": 3.0}, {"rank": 8, "name": "f3fka7", "viewers": 944, "share_pct": 2.8}, {"rank": 9, "name": "keliencs", "viewers": 891, "share_pct": 2.6}, {"rank": 10, "name": "anastaze", "viewers": 838, "share_pct": 2.5}], "IRL": [{"rank": 1, "name": "OniGiri", "viewers": 3238, "share_pct": 10.7}, {"rank": 2, "name": "Kunshikitty", "viewers": 2217, "share_pct": 7.4}, {"rank": 3, "name": "Chloe__IRL", "viewers": 1908, "share_pct": 6.3}, {"rank": 4, "name": "MinusElf", "viewers": 1591, "share_pct": 5.3}, {"rank": 5, "name": "Karni", "viewers": 1196, "share_pct": 4.0}, {"rank": 6, "name": "EpicVoyages", "viewers": 1166, "share_pct": 3.9}, {"rank": 7, "name": "meetenshow", "viewers": 992, "share_pct": 3.3}, {"rank": 8, "name": "JardiStream", "viewers": 816, "share_pct": 2.7}, {"rank": 9, "name": "PeeguuTV", "viewers": 814, "share_pct": 2.7}, {"rank": 10, "name": "\u304c\u30fc\u3069\u307e\u3093", "viewers": 689, "share_pct": 2.3}], "Grand Theft Auto V": [{"rank": 1, "name": "jungjiwtf", "viewers": 1485, "share_pct": 7.8}, {"rank": 2, "name": "jerzy", "viewers": 712, "share_pct": 3.7}, {"rank": 3, "name": "babykala", "viewers": 538, "share_pct": 2.8}, {"rank": 4, "name": "Kiilanie", "viewers": 534, "share_pct": 2.8}, {"rank": 5, "name": "olivkatattoo", "viewers": 519, "share_pct": 2.7}, {"rank": 6, "name": "nelk0r", "viewers": 502, "share_pct": 2.6}, {"rank": 7, "name": "LusorKoeffizient", "viewers": 440, "share_pct": 2.3}, {"rank": 8, "name": "Pepe_The_Rarest", "viewers": 439, "share_pct": 2.3}, {"rank": 9, "name": "Sackzi", "viewers": 396, "share_pct": 2.1}], "World of Warcraft": [{"rank": 1, "name": "Guzu", "viewers": 1793, "share_pct": 8.8}, {"rank": 2, "name": "JokerdTV", "viewers": 1790, "share_pct": 8.8}, {"rank": 3, "name": "dafran", "viewers": 987, "share_pct": 4.9}, {"rank": 4, "name": "sunglitters", "viewers": 950, "share_pct": 4.7}, {"rank": 5, "name": "C_a_k_e", "viewers": 912, "share_pct": 4.5}, {"rank": 6, "name": "DerHauge", "viewers": 874, "share_pct": 4.3}, {"rank": 7, "name": "lizotika", "viewers": 681, "share_pct": 3.4}, {"rank": 8, "name": "Ziqoftw", "viewers": 639, "share_pct": 3.2}, {"rank": 9, "name": "Peettko", "viewers": 540, "share_pct": 2.7}, {"rank": 10, "name": "Dekel", "viewers": 536, "share_pct": 2.6}], "Fortnite": [{"rank": 1, "name": "Gingy", "viewers": 4310, "share_pct": 26.8}, {"rank": 2, "name": "Loeya", "viewers": 1699, "share_pct": 10.6}, {"rank": 3, "name": "Oatley", "viewers": 1089, "share_pct": 6.8}, {"rank": 4, "name": "Ache", "viewers": 1069, "share_pct": 6.7}, {"rank": 5, "name": "Recuerd0p", "viewers": 499, "share_pct": 3.1}, {"rank": 6, "name": "OShakOnIG", "viewers": 410, "share_pct": 2.6}, {"rank": 7, "name": "can78aux", "viewers": 294, "share_pct": 1.8}, {"rank": 8, "name": "levilaingarc0n", "viewers": 245, "share_pct": 1.5}, {"rank": 9, "name": "itsvicterv", "viewers": 240, "share_pct": 1.5}], "Dead by Daylight": [{"rank": 1, "name": "LittleSpaceRock", "viewers": 1361, "share_pct": 7.9}, {"rank": 2, "name": "spitzz", "viewers": 1093, "share_pct": 6.3}, {"rank": 3, "name": "TrU3Ta1ent", "viewers": 931, "share_pct": 5.4}, {"rank": 4, "name": "schaendus", "viewers": 642, "share_pct": 3.7}, {"rank": 5, "name": "SwehYT", "viewers": 549, "share_pct": 3.2}, {"rank": 6, "name": "OllyBOT", "viewers": 516, "share_pct": 3.0}, {"rank": 7, "name": "Proxhy", "viewers": 379, "share_pct": 2.2}, {"rank": 8, "name": "Jescheska", "viewers": 367, "share_pct": 2.1}, {"rank": 9, "name": "Swii", "viewers": 364, "share_pct": 2.1}, {"rank": 10, "name": "TonytheDuff", "viewers": 306, "share_pct": 1.8}], "ELDEN RING NIGHTREIGN": [{"rank": 1, "name": "stylishnoob4", "viewers": 16221, "share_pct": 93.8}, {"rank": 2, "name": "iSkys", "viewers": 182, "share_pct": 1.1}, {"rank": 3, "name": "LANTlC", "viewers": 176, "share_pct": 1.0}, {"rank": 4, "name": "ThatsTheFeesh", "viewers": 111, "share_pct": 0.6}, {"rank": 5, "name": "katha", "viewers": 58, "share_pct": 0.3}, {"rank": 6, "name": "dudley", "viewers": 58, "share_pct": 0.3}, {"rank": 7, "name": "stellardasha", "viewers": 45, "share_pct": 0.3}, {"rank": 8, "name": "\u3082\u3075\u3081\u3047\u3053", "viewers": 45, "share_pct": 0.3}, {"rank": 9, "name": "\u304b\u3061\u3085\u3046", "viewers": 43, "share_pct": 0.2}, {"rank": 10, "name": "arwwa", "viewers": 42, "share_pct": 0.2}], "Sparkster": [{"rank": 1, "name": "GamesDoneQuick", "viewers": 14457, "share_pct": null}, {"rank": 2, "name": "japanese_restream", "viewers": 1220, "share_pct": null}], "Always On": [{"rank": 1, "name": "TheBurntPeanut_247", "viewers": 1520, "share_pct": 10.0}, {"rank": 2, "name": "LacyOffline_", "viewers": 1471, "share_pct": 9.7}, {"rank": 3, "name": "Cohh", "viewers": 1111, "share_pct": 7.3}, {"rank": 4, "name": "247Jynxzi", "viewers": 733, "share_pct": 4.8}, {"rank": 5, "name": "CineIlloJuan", "viewers": 649, "share_pct": 4.3}, {"rank": 6, "name": "ChilledChaos", "viewers": 426, "share_pct": 2.8}, {"rank": 7, "name": "ArmandoForceVOD", "viewers": 408, "share_pct": 2.7}, {"rank": 8, "name": "RiffTrax", "viewers": 353, "share_pct": 2.3}, {"rank": 9, "name": "RdcWaitingRoom_", "viewers": 352, "share_pct": 2.3}, {"rank": 10, "name": "AltairNative", "viewers": 343, "share_pct": 2.3}], "Sports": [{"rank": 1, "name": "gerardromero", "viewers": 4072, "share_pct": 26.4}, {"rank": 2, "name": "\u5bcc\u90a6\u608d\u5c07\u5b98\u65b9\u983b\u9053", "viewers": 3142, "share_pct": 20.4}, {"rank": 3, "name": "valentisanjuan", "viewers": 2018, "share_pct": 13.1}, {"rank": 4, "name": "ElChiringuitoTV", "viewers": 1403, "share_pct": 9.1}, {"rank": 5, "name": "Juventibus", "viewers": 842, "share_pct": 5.5}, {"rank": 6, "name": "\u608d\u5c07\u61c9\u63f4\u82b1\u7d6e\u983b\u9053", "viewers": 704, "share_pct": 4.6}, {"rank": 7, "name": "LaGradaOnline", "viewers": 641, "share_pct": 4.2}, {"rank": 8, "name": "INAKIANGULOTV", "viewers": 619, "share_pct": 4.0}, {"rank": 9, "name": "teladoiotokyo", "viewers": 459, "share_pct": 3.0}, {"rank": 10, "name": "LaGrada914", "viewers": 247, "share_pct": 1.6}], "Overwatch": [{"rank": 1, "name": "iddqd", "viewers": 1487, "share_pct": 13.5}, {"rank": 2, "name": "getrush_7", "viewers": 1085, "share_pct": 9.9}, {"rank": 3, "name": "yaycandi", "viewers": 595, "share_pct": 5.4}, {"rank": 4, "name": "\u4ef2\u9054", "viewers": 556, "share_pct": 5.1}, {"rank": 5, "name": "Winton_OW2", "viewers": 525, "share_pct": 4.8}, {"rank": 6, "name": "PLAYTO_ow", "viewers": 335, "share_pct": 3.0}, {"rank": 7, "name": "\u308a\u3044\u305f\u307e", "viewers": 300, "share_pct": 2.7}, {"rank": 8, "name": "hadi_ow", "viewers": 292, "share_pct": 2.7}], "Marvel Rivals": [{"rank": 1, "name": "GURU", "viewers": 2057, "share_pct": 15.7}, {"rank": 2, "name": "Ariella", "viewers": 1655, "share_pct": 12.7}, {"rank": 3, "name": "kragiee", "viewers": 1181, "share_pct": 9.0}, {"rank": 4, "name": "zazzastack", "viewers": 786, "share_pct": 6.0}, {"rank": 5, "name": "peach", "viewers": 491, "share_pct": 3.8}, {"rank": 6, "name": "cichwiz", "viewers": 441, "share_pct": 3.4}, {"rank": 7, "name": "HoriJey_", "viewers": 346, "share_pct": 2.6}, {"rank": 8, "name": "\u5b99\u661f\u3071\u308b", "viewers": 256, "share_pct": 2.0}, {"rank": 9, "name": "snakeCase2", "viewers": 201, "share_pct": 1.5}, {"rank": 10, "name": "BersGamer", "viewers": 189, "share_pct": 1.4}], "Hearthstone": [{"rank": 1, "name": "Uzra", "viewers": 2335, "share_pct": 18.8}, {"rank": 2, "name": "RduLIVE", "viewers": 1329, "share_pct": 10.7}, {"rank": 3, "name": "ixxdeee", "viewers": 1262, "share_pct": 10.1}, {"rank": 4, "name": "\u856d\u653f\u9298", "viewers": 787, "share_pct": 6.3}, {"rank": 5, "name": "Zetalot", "viewers": 712, "share_pct": 5.7}, {"rank": 6, "name": "SolaryHS", "viewers": 709, "share_pct": 5.7}, {"rank": 7, "name": "advocate_hs", "viewers": 515, "share_pct": 4.1}, {"rank": 8, "name": "\u8c46\u8c46", "viewers": 487, "share_pct": 3.9}, {"rank": 9, "name": "ALOHADANCETV", "viewers": 448, "share_pct": 3.6}, {"rank": 10, "name": "Nik1taStar", "viewers": 346, "share_pct": 2.8}], "Escape from Tarkov": [{"rank": 1, "name": "Dunduk", "viewers": 3228, "share_pct": 28.3}, {"rank": 2, "name": "Glorious_E", "viewers": 3016, "share_pct": 26.4}, {"rank": 3, "name": "AIMLUL", "viewers": 1193, "share_pct": 10.4}, {"rank": 4, "name": "dahmien7", "viewers": 371, "share_pct": 3.2}, {"rank": 5, "name": "Skuuii", "viewers": 238, "share_pct": 2.1}, {"rank": 6, "name": "h4rd111", "viewers": 221, "share_pct": 1.9}, {"rank": 7, "name": "GgSanTomE", "viewers": 189, "share_pct": 1.7}, {"rank": 8, "name": "yeahunter", "viewers": 178, "share_pct": 1.6}, {"rank": 9, "name": "\u307f\u3084\u307e\u308b\u3060\u3088", "viewers": 152, "share_pct": 1.3}, {"rank": 10, "name": "FIOLOCHKA", "viewers": 128, "share_pct": 1.1}], "Minecraft": [{"rank": 1, "name": "Alcest_M", "viewers": 629, "share_pct": 7.0}, {"rank": 2, "name": "Diamkey", "viewers": 305, "share_pct": 3.4}, {"rank": 3, "name": "STAMSITE", "viewers": 302, "share_pct": 3.4}, {"rank": 4, "name": "zarbex_TV", "viewers": 268, "share_pct": 3.0}, {"rank": 5, "name": "TENNN", "viewers": 242, "share_pct": 2.7}, {"rank": 6, "name": "Button", "viewers": 210, "share_pct": 2.3}, {"rank": 7, "name": "7rowl", "viewers": 176, "share_pct": 2.0}, {"rank": 8, "name": "MayaIcefire", "viewers": 149, "share_pct": 1.7}, {"rank": 9, "name": "Hoef", "viewers": 149, "share_pct": 1.7}], "Rainbow Six Siege": [{"rank": 1, "name": "Rainbow6", "viewers": 7785, "share_pct": 78.9}, {"rank": 2, "name": "BikiniBodhi", "viewers": 149, "share_pct": 1.5}, {"rank": 3, "name": "vetelcito01", "viewers": 136, "share_pct": 1.4}, {"rank": 4, "name": "masamitzu", "viewers": 113, "share_pct": 1.1}, {"rank": 5, "name": "KingGeorgeOffline", "viewers": 112, "share_pct": 1.1}, {"rank": 6, "name": "Hercxules", "viewers": 95, "share_pct": 1.0}, {"rank": 7, "name": "Sha77eTV", "viewers": 82, "share_pct": 0.8}, {"rank": 8, "name": "pascal0_4", "viewers": 79, "share_pct": 0.8}, {"rank": 9, "name": "\u82e5\u51cc_", "viewers": 73, "share_pct": 0.7}, {"rank": 10, "name": "Nayqo7k", "viewers": 65, "share_pct": 0.7}], "PUBG: BATTLEGROUNDS": [{"rank": 1, "name": "kinapoppo", "viewers": 1274, "share_pct": 13.5}, {"rank": 2, "name": "AlphaAzur", "viewers": 728, "share_pct": 7.7}, {"rank": 3, "name": "Bonkol", "viewers": 709, "share_pct": 7.5}, {"rank": 4, "name": "\u4e7e\u4f38\u4e00\u90ce", "viewers": 686, "share_pct": 7.3}, {"rank": 5, "name": "Killin9Hit", "viewers": 665, "share_pct": 7.0}, {"rank": 6, "name": "marty_vole", "viewers": 485, "share_pct": 5.1}, {"rank": 7, "name": "GeTManueL", "viewers": 408, "share_pct": 4.3}, {"rank": 8, "name": "zuluxxman", "viewers": 351, "share_pct": 3.7}, {"rank": 9, "name": "mirzalievmma", "viewers": 340, "share_pct": 3.6}, {"rank": 10, "name": "PUBGThailandOfficial", "viewers": 334, "share_pct": 3.5}], "Powerful Pro Yakyuu 2026-2027": [{"rank": 1, "name": "\u305f\u3044\u3058_\u305f\u3044\u3061\u3083\u3093\u306d\u308b", "viewers": 7863, "share_pct": 87.0}, {"rank": 2, "name": "\u30b5\u30ab\u30ca\u30a4\u30f3", "viewers": 548, "share_pct": 6.1}, {"rank": 3, "name": "\u30ce\u30d3\u30fc\u30fc", "viewers": 263, "share_pct": 2.9}, {"rank": 4, "name": "\u7a7a\u8863\u5fa1\u4f8d", "viewers": 156, "share_pct": 1.7}, {"rank": 5, "name": "\u304b\u3066\u3043\u3055\u3093", "viewers": 106, "share_pct": 1.2}, {"rank": 6, "name": "\u3046\u3069\u3093\u304a\u59c9\u3061\u3083\u3093", "viewers": 76, "share_pct": 0.8}, {"rank": 7, "name": "\u30cb\u30fc\u592a", "viewers": 27, "share_pct": 0.3}, {"rank": 8, "name": "\u307e\u3061\u3083\u3053", "viewers": 4, "share_pct": 0.0}, {"rank": 9, "name": "\u304b\u305a\u3061\u3083\u3093\u3060\u3088", "viewers": 3, "share_pct": 0.0}, {"rank": 10, "name": "ymjsr", "viewers": 3, "share_pct": 0.0}], "Slots": [{"rank": 1, "name": "t1mson_prime", "viewers": 760, "share_pct": 9.1}, {"rank": 2, "name": "CasinoDaddy", "viewers": 655, "share_pct": 7.8}, {"rank": 3, "name": "gigicasper", "viewers": 427, "share_pct": 5.1}, {"rank": 4, "name": "fleekzie19", "viewers": 390, "share_pct": 4.7}, {"rank": 5, "name": "olamanja", "viewers": 388, "share_pct": 4.6}, {"rank": 6, "name": "Faraich3", "viewers": 325, "share_pct": 3.9}, {"rank": 7, "name": "gTastySlots", "viewers": 292, "share_pct": 3.5}, {"rank": 8, "name": "pakkunfps", "viewers": 286, "share_pct": 3.4}, {"rank": 9, "name": "luckvex", "viewers": 260, "share_pct": 3.1}, {"rank": 10, "name": "OMendigoTV", "viewers": 232, "share_pct": 2.8}], "MECCHA CHAMELEON": [{"rank": 1, "name": "SuperJJ", "viewers": 897, "share_pct": 9.9}, {"rank": 2, "name": "\u5deb\u795e\u3053\u3093", "viewers": 635, "share_pct": 7.0}, {"rank": 3, "name": "LexiGraham", "viewers": 608, "share_pct": 6.7}, {"rank": 4, "name": "\u3078\u3066\u308b", "viewers": 490, "share_pct": 5.4}, {"rank": 5, "name": "WorstPremadeEver", "viewers": 365, "share_pct": 4.0}, {"rank": 6, "name": "\u3068\u3093\u307c\u3067\u3059", "viewers": 348, "share_pct": 3.8}, {"rank": 7, "name": "\u30b6\u30af\u30ec\u30a4", "viewers": 309, "share_pct": 3.4}, {"rank": 8, "name": "Autophil", "viewers": 279, "share_pct": 3.1}, {"rank": 9, "name": "Shyraa", "viewers": 265, "share_pct": 2.9}, {"rank": 10, "name": "Lumenti", "viewers": 261, "share_pct": 2.9}], "Call of Duty: Warzone": [{"rank": 1, "name": "Zyro", "viewers": 740, "share_pct": 9.4}, {"rank": 2, "name": "fifakillvizualz", "viewers": 641, "share_pct": 8.1}, {"rank": 3, "name": "V1nKub", "viewers": 508, "share_pct": 6.4}, {"rank": 4, "name": "etokeking", "viewers": 400, "share_pct": 5.1}, {"rank": 5, "name": "INFINITE_SGE", "viewers": 316, "share_pct": 4.0}, {"rank": 6, "name": "Nianfo", "viewers": 259, "share_pct": 3.3}, {"rank": 7, "name": "BennyCentral", "viewers": 259, "share_pct": 3.3}, {"rank": 8, "name": "bigdaddygmann", "viewers": 252, "share_pct": 3.2}, {"rank": 9, "name": "Jukeyz", "viewers": 225, "share_pct": 2.8}, {"rank": 10, "name": "MissPurple", "viewers": 192, "share_pct": 2.4}], "HUNGER": [{"rank": 1, "name": "Sequisha", "viewers": 2448, "share_pct": 29.7}, {"rank": 2, "name": "BIGRUSSIANMUM", "viewers": 1830, "share_pct": 22.2}, {"rank": 3, "name": "2TwistedTV", "viewers": 518, "share_pct": 6.3}, {"rank": 4, "name": "BreaK", "viewers": 502, "share_pct": 6.1}, {"rank": 5, "name": "REXNOR", "viewers": 410, "share_pct": 5.0}, {"rank": 6, "name": "Ranzratte", "viewers": 325, "share_pct": 3.9}, {"rank": 7, "name": "TwoAngryGamersTV", "viewers": 265, "share_pct": 3.2}, {"rank": 8, "name": "Maplewood_tv", "viewers": 221, "share_pct": 2.7}, {"rank": 9, "name": "TORRO", "viewers": 215, "share_pct": 2.6}, {"rank": 10, "name": "wjuh", "viewers": 209, "share_pct": 2.5}], "Path of Exile 2": [{"rank": 1, "name": "singsing", "viewers": 1209, "share_pct": 16.5}, {"rank": 2, "name": "b0b5", "viewers": 725, "share_pct": 9.9}, {"rank": 3, "name": "DEADRABB1T", "viewers": 621, "share_pct": 8.5}, {"rank": 4, "name": "Steelmage", "viewers": 539, "share_pct": 7.4}, {"rank": 5, "name": "Memorizer", "viewers": 377, "share_pct": 5.2}, {"rank": 6, "name": "redviles", "viewers": 342, "share_pct": 4.7}, {"rank": 7, "name": "iamjustacrazy", "viewers": 328, "share_pct": 4.5}, {"rank": 8, "name": "MisoxShiru", "viewers": 233, "share_pct": 3.2}, {"rank": 9, "name": "KingKongor", "viewers": 192, "share_pct": 2.6}], "Art": [{"rank": 1, "name": "\ub808\ube44\uc544\ud0c412", "viewers": 144, "share_pct": 2.1}, {"rank": 2, "name": "\u7dbf\u7fbd\u30df\u30eb\u30d5\u30a3", "viewers": 138, "share_pct": 2.0}, {"rank": 3, "name": "mikamuse", "viewers": 131, "share_pct": 1.9}, {"rank": 4, "name": "symon_redd", "viewers": 124, "share_pct": 1.8}, {"rank": 5, "name": "Teikki_", "viewers": 121, "share_pct": 1.7}, {"rank": 6, "name": "marshmallowpandaa", "viewers": 109, "share_pct": 1.6}, {"rank": 7, "name": "\u4e5d\u6afb", "viewers": 102, "share_pct": 1.5}, {"rank": 8, "name": "DaysofRika", "viewers": 101, "share_pct": 1.5}, {"rank": 9, "name": "LallaWaffle", "viewers": 86, "share_pct": 1.2}], "Assassin's Creed Black Flag Resynced": [{"rank": 1, "name": "Rivenzi", "viewers": 1825, "share_pct": 25.3}, {"rank": 2, "name": "Repaz", "viewers": 1467, "share_pct": 20.3}, {"rank": 3, "name": "PaigeTheWitch", "viewers": 916, "share_pct": 12.7}, {"rank": 4, "name": "Grumbul", "viewers": 390, "share_pct": 5.4}, {"rank": 5, "name": "DerHardi", "viewers": 386, "share_pct": 5.3}, {"rank": 6, "name": "RatAttitude", "viewers": 345, "share_pct": 4.8}, {"rank": 7, "name": "Larsi", "viewers": 308, "share_pct": 4.3}, {"rank": 8, "name": "bulletthekrazygamer", "viewers": 232, "share_pct": 3.2}, {"rank": 9, "name": "teegstah", "viewers": 184, "share_pct": 2.5}, {"rank": 10, "name": "Aimbrot", "viewers": 154, "share_pct": 2.1}], "World of Tanks": [{"rank": 1, "name": "Orzanel", "viewers": 2013, "share_pct": 30.9}, {"rank": 2, "name": "AwesomeEpicGuys", "viewers": 429, "share_pct": 6.6}, {"rank": 3, "name": "Chessgenie", "viewers": 413, "share_pct": 6.3}, {"rank": 4, "name": "L4ny_", "viewers": 357, "share_pct": 5.5}, {"rank": 5, "name": "sh0kerix", "viewers": 351, "share_pct": 5.4}, {"rank": 6, "name": "FC_DYNAMO", "viewers": 259, "share_pct": 4.0}, {"rank": 7, "name": "samiyka", "viewers": 218, "share_pct": 3.3}, {"rank": 8, "name": "KamilEater", "viewers": 201, "share_pct": 3.1}, {"rank": 9, "name": "KECAJEK", "viewers": 183, "share_pct": 2.8}, {"rank": 10, "name": "hirvonnen", "viewers": 166, "share_pct": 2.5}], "ARC Raiders": [{"rank": 1, "name": "TheGamingMerchant", "viewers": 1745, "share_pct": 29.2}, {"rank": 2, "name": "LEV_BRITVAAA", "viewers": 710, "share_pct": 11.9}, {"rank": 3, "name": "ShinyaTheNinja", "viewers": 459, "share_pct": 7.7}, {"rank": 4, "name": "lyesval", "viewers": 409, "share_pct": 6.8}, {"rank": 5, "name": "JSavageW", "viewers": 307, "share_pct": 5.1}, {"rank": 6, "name": "tenseyka", "viewers": 153, "share_pct": 2.6}, {"rank": 7, "name": "mizzake", "viewers": 121, "share_pct": 2.0}, {"rank": 8, "name": "Zoon", "viewers": 115, "share_pct": 1.9}, {"rank": 9, "name": "EinfachMaik_", "viewers": 103, "share_pct": 1.7}, {"rank": 10, "name": "XOROSHAYAVIKUSIA", "viewers": 94, "share_pct": 1.6}], "ASMR": [{"rank": 1, "name": "telishamaree", "viewers": 1262, "share_pct": 20.6}, {"rank": 2, "name": "Lovella", "viewers": 658, "share_pct": 10.8}, {"rank": 3, "name": "poxiia", "viewers": 509, "share_pct": 8.3}, {"rank": 4, "name": "Lilithh", "viewers": 432, "share_pct": 7.1}, {"rank": 5, "name": "Saora", "viewers": 401, "share_pct": 6.6}, {"rank": 6, "name": "Braver_Kyubei", "viewers": 300, "share_pct": 4.9}, {"rank": 7, "name": "SharonQueen", "viewers": 244, "share_pct": 4.0}, {"rank": 8, "name": "KaileyMaeASMR", "viewers": 215, "share_pct": 3.5}, {"rank": 9, "name": "\u4f50\u85e4\u3061\u3086\u308a", "viewers": 174, "share_pct": 2.8}, {"rank": 10, "name": "Tingting57", "viewers": 154, "share_pct": 2.5}], "Delta Force": [{"rank": 1, "name": "\u6bba\u6897", "viewers": 694, "share_pct": 11.9}, {"rank": 2, "name": "\u8336\u5e3d\u746a\u7df9", "viewers": 541, "share_pct": 9.3}, {"rank": 3, "name": "Leissik", "viewers": 476, "share_pct": 8.1}, {"rank": 4, "name": "9QOQ", "viewers": 436, "share_pct": 7.5}, {"rank": 5, "name": "\u7fd4\u592a\u3067\u3059", "viewers": 313, "share_pct": 5.4}, {"rank": 6, "name": "\u5c0f\u4f0a\u4f0a", "viewers": 303, "share_pct": 5.2}, {"rank": 7, "name": "EqualPlays", "viewers": 243, "share_pct": 4.2}, {"rank": 8, "name": "cook_playing", "viewers": 199, "share_pct": 3.4}, {"rank": 9, "name": "stikinson", "viewers": 190, "share_pct": 3.3}, {"rank": 10, "name": "Mendo", "viewers": 169, "share_pct": 2.9}], "ARK: Survival Ascended": [{"rank": 1, "name": "\u606d\u4e00\u90ce", "viewers": 2688, "share_pct": 46.2}, {"rank": 2, "name": "\u308d\u305c\u3063\u304f\u3074\u3093", "viewers": 786, "share_pct": 13.5}, {"rank": 3, "name": "shockist", "viewers": 348, "share_pct": 6.0}, {"rank": 4, "name": "Omnikevfka", "viewers": 238, "share_pct": 4.1}, {"rank": 5, "name": "CletusBueford", "viewers": 187, "share_pct": 3.2}, {"rank": 6, "name": "\u7070\u30ce\u9f20\u3057\u306a\u306e", "viewers": 141, "share_pct": 2.4}, {"rank": 7, "name": "Gingarella", "viewers": 122, "share_pct": 2.1}, {"rank": 8, "name": "Dark_Seras", "viewers": 88, "share_pct": 1.5}, {"rank": 9, "name": "Usya", "viewers": 68, "share_pct": 1.2}, {"rank": 10, "name": "DoonGrachtome", "viewers": 67, "share_pct": 1.2}], "EA Sports FC 26": [{"rank": 1, "name": "Stokes", "viewers": 1397, "share_pct": 25.1}, {"rank": 2, "name": "German_intelligence", "viewers": 601, "share_pct": 10.8}, {"rank": 3, "name": "xpazzoo", "viewers": 524, "share_pct": 9.4}, {"rank": 4, "name": "Zazzone230", "viewers": 407, "share_pct": 7.3}, {"rank": 5, "name": "Der_Gaucho10", "viewers": 182, "share_pct": 3.3}, {"rank": 6, "name": "RiberaRibell", "viewers": 156, "share_pct": 2.8}, {"rank": 7, "name": "miguez01", "viewers": 140, "share_pct": 2.5}, {"rank": 8, "name": "eadriaticleague01", "viewers": 136, "share_pct": 2.4}, {"rank": 9, "name": "acoolbek", "viewers": 130, "share_pct": 2.3}, {"rank": 10, "name": "eadriaticleaguetwo", "viewers": 129, "share_pct": 2.3}], "Teamfight Tactics": [{"rank": 1, "name": "\u7da0\u8336", "viewers": 1935, "share_pct": 32.8}, {"rank": 2, "name": "LPGjustJohnny", "viewers": 1117, "share_pct": 18.9}, {"rank": 3, "name": "keanelol", "viewers": 1005, "share_pct": 17.0}, {"rank": 4, "name": "rykomastery_", "viewers": 400, "share_pct": 6.8}, {"rank": 5, "name": "triciaisabirdy", "viewers": 223, "share_pct": 3.8}, {"rank": 6, "name": "Keola", "viewers": 170, "share_pct": 2.9}, {"rank": 7, "name": "kes080", "viewers": 123, "share_pct": 2.1}, {"rank": 8, "name": "PommeDeTFTerre", "viewers": 82, "share_pct": 1.4}, {"rank": 9, "name": "higress", "viewers": 79, "share_pct": 1.3}, {"rank": 10, "name": "\u68a6\u7d50\u307f\u3081\u3044", "viewers": 75, "share_pct": 1.3}], "Animals, Aquariums, and Zoos": [{"rank": 1, "name": "AlveusSanctuary", "viewers": 1482, "share_pct": 27.5}, {"rank": 2, "name": "Shrimps247", "viewers": 407, "share_pct": 7.6}, {"rank": 3, "name": "FerretSoftware", "viewers": 369, "share_pct": 6.9}, {"rank": 4, "name": "DashDucks", "viewers": 280, "share_pct": 5.2}, {"rank": 5, "name": "MarineMammalRescue", "viewers": 264, "share_pct": 4.9}, {"rank": 6, "name": "Suggieland", "viewers": 256, "share_pct": 4.8}, {"rank": 7, "name": "Furball_Farm", "viewers": 237, "share_pct": 4.4}, {"rank": 8, "name": "\u5167\u57d4\u8591\u6bcd\u9d28", "viewers": 183, "share_pct": 3.4}, {"rank": 9, "name": "WildLifeCam", "viewers": 150, "share_pct": 2.8}, {"rank": 10, "name": "QBunnyTV", "viewers": 136, "share_pct": 2.5}], "Street Fighter 6": [{"rank": 1, "name": "\u306a\u308b\u304a_", "viewers": 1943, "share_pct": 35.8}, {"rank": 2, "name": "\u5929\u5e1d\u30d5\u30a9\u30eb\u30c6", "viewers": 961, "share_pct": 17.7}, {"rank": 3, "name": "kenbogard", "viewers": 593, "share_pct": 10.9}, {"rank": 4, "name": "SchiacciSempreTV", "viewers": 148, "share_pct": 2.7}, {"rank": 5, "name": "\u305f\u305f\u304b\u3048\uff6f\u3070\u3076\u592a\u90ce", "viewers": 129, "share_pct": 2.4}, {"rank": 6, "name": "\u306a\u304b\u3082\u3068\u304a\u307e\u3061", "viewers": 116, "share_pct": 2.1}, {"rank": 7, "name": "\u308d\u3073\u3093\u3073\u3093", "viewers": 110, "share_pct": 2.0}, {"rank": 8, "name": "Yuffie", "viewers": 106, "share_pct": 2.0}, {"rank": 9, "name": "\u677f\u6a4b\u5c0f\u7d50\u5df4", "viewers": 86, "share_pct": 1.6}, {"rank": 10, "name": "\u3088\u3063\u3055\u30930209", "viewers": 67, "share_pct": 1.2}], "Albion Online": [{"rank": 1, "name": "ElPelotasssss", "viewers": 1425, "share_pct": 28.8}, {"rank": 2, "name": "FroggyJolson", "viewers": 863, "share_pct": 17.4}, {"rank": 3, "name": "Fakturka", "viewers": 431, "share_pct": 8.7}, {"rank": 4, "name": "Char1ynn", "viewers": 323, "share_pct": 6.5}, {"rank": 5, "name": "ZyfraRaider", "viewers": 282, "share_pct": 5.7}, {"rank": 6, "name": "SummerSeaChels", "viewers": 276, "share_pct": 5.6}, {"rank": 7, "name": "PatoAlbion", "viewers": 246, "share_pct": 5.0}, {"rank": 8, "name": "Youby4", "viewers": 184, "share_pct": 3.7}, {"rank": 9, "name": "Neamhel", "viewers": 138, "share_pct": 2.8}, {"rank": 10, "name": "Lilith", "viewers": 128, "share_pct": 2.6}], "Rhythm Heaven Groove": [{"rank": 1, "name": "\u8d64\u898b\u304b\u308b\u3073", "viewers": 3010, "share_pct": 57.4}, {"rank": 2, "name": "\u5929\u7fbd\u3088\u3064\u306f", "viewers": 457, "share_pct": 8.7}, {"rank": 3, "name": "ade3_3", "viewers": 258, "share_pct": 4.9}, {"rank": 4, "name": "Skuru", "viewers": 217, "share_pct": 4.1}, {"rank": 5, "name": "\u30ec\u30c4", "viewers": 210, "share_pct": 4.0}, {"rank": 6, "name": "\u9675\u672c\u306a\u304e", "viewers": 204, "share_pct": 3.9}, {"rank": 7, "name": "\u771f\u6f84\u305b\u3093\u306e", "viewers": 119, "share_pct": 2.3}, {"rank": 8, "name": "\u304a\u3072\u3064\u3058\u3081\u3047", "viewers": 102, "share_pct": 1.9}, {"rank": 9, "name": "caaaaate", "viewers": 77, "share_pct": 1.5}, {"rank": 10, "name": "\u3079\u3053\u3049", "viewers": 69, "share_pct": 1.3}], "Lycans": [{"rank": 1, "name": "Ponce", "viewers": 3973, "share_pct": 76.5}, {"rank": 2, "name": "ToneEUW", "viewers": 234, "share_pct": 4.5}, {"rank": 3, "name": "Flonflon", "viewers": 168, "share_pct": 3.2}, {"rank": 4, "name": "Raumane", "viewers": 159, "share_pct": 3.1}, {"rank": 5, "name": "Kha_LeN", "viewers": 151, "share_pct": 2.9}, {"rank": 6, "name": "KAOsvmd", "viewers": 141, "share_pct": 2.7}, {"rank": 7, "name": "Tsunadida", "viewers": 135, "share_pct": 2.6}, {"rank": 8, "name": "Bytell2", "viewers": 99, "share_pct": 1.9}, {"rank": 9, "name": "MathyMoon", "viewers": 53, "share_pct": 1.0}, {"rank": 10, "name": "Tamaroush_", "viewers": 32, "share_pct": 0.6}], "I'm Only Sleeping": [{"rank": 1, "name": "wehoopinx", "viewers": 589, "share_pct": 11.8}, {"rank": 2, "name": "sheviii2k", "viewers": 502, "share_pct": 10.1}, {"rank": 3, "name": "SincerelyAurora", "viewers": 327, "share_pct": 6.6}, {"rank": 4, "name": "necronival", "viewers": 232, "share_pct": 4.7}, {"rank": 5, "name": "Leopard", "viewers": 196, "share_pct": 3.9}, {"rank": 6, "name": "Buttsoap", "viewers": 193, "share_pct": 3.9}, {"rank": 7, "name": "AsianJeff", "viewers": 178, "share_pct": 3.6}, {"rank": 8, "name": "jorge", "viewers": 172, "share_pct": 3.5}, {"rank": 9, "name": "Szzalony", "viewers": 150, "share_pct": 3.0}, {"rank": 10, "name": "HMBLZAYY", "viewers": 145, "share_pct": 2.9}], "Diablo IV": [{"rank": 1, "name": "wudijo", "viewers": 1407, "share_pct": 29.1}, {"rank": 2, "name": "Rob2628", "viewers": 1189, "share_pct": 24.6}, {"rank": 3, "name": "P4wnyhof", "viewers": 625, "share_pct": 12.9}, {"rank": 4, "name": "kypced", "viewers": 131, "share_pct": 2.7}, {"rank": 5, "name": "VegaDiablo", "viewers": 102, "share_pct": 2.1}, {"rank": 6, "name": "MakinDoe", "viewers": 100, "share_pct": 2.1}, {"rank": 7, "name": "Courone", "viewers": 83, "share_pct": 1.7}, {"rank": 8, "name": "bittersweetraz", "viewers": 80, "share_pct": 1.7}, {"rank": 9, "name": "AnnacakeLIVE", "viewers": 80, "share_pct": 1.7}, {"rank": 10, "name": "PandaTV", "viewers": 73, "share_pct": 1.5}], "Old School RuneScape": [{"rank": 1, "name": "Westham", "viewers": 768, "share_pct": 15.4}, {"rank": 2, "name": "EvScape", "viewers": 665, "share_pct": 13.4}, {"rank": 3, "name": "Dino_xx", "viewers": 537, "share_pct": 10.8}, {"rank": 4, "name": "Skiddler", "viewers": 467, "share_pct": 9.4}, {"rank": 5, "name": "Verf", "viewers": 404, "share_pct": 8.1}, {"rank": 6, "name": "myaahhh", "viewers": 241, "share_pct": 4.8}, {"rank": 7, "name": "Viikonloppu", "viewers": 230, "share_pct": 4.6}, {"rank": 8, "name": "Autumneev", "viewers": 175, "share_pct": 3.5}, {"rank": 9, "name": "ItsIvy", "viewers": 141, "share_pct": 2.8}, {"rank": 10, "name": "Ammy9", "viewers": 115, "share_pct": 2.3}], "Arena Breakout: Infinite": [{"rank": 1, "name": "samoylov___", "viewers": 827, "share_pct": 17.6}, {"rank": 2, "name": "THE_IKEN", "viewers": 602, "share_pct": 12.8}, {"rank": 3, "name": "ShamiXX", "viewers": 402, "share_pct": 8.5}, {"rank": 4, "name": "SuraFPS", "viewers": 349, "share_pct": 7.4}, {"rank": 5, "name": "kassshiro", "viewers": 347, "share_pct": 7.4}, {"rank": 6, "name": "Buggy", "viewers": 227, "share_pct": 4.8}, {"rank": 7, "name": "TARAS0V99", "viewers": 119, "share_pct": 2.5}, {"rank": 8, "name": "HuntsGG", "viewers": 112, "share_pct": 2.4}, {"rank": 9, "name": "Miniuwa", "viewers": 101, "share_pct": 2.1}, {"rank": 10, "name": "ButcherCrispyBones", "viewers": 97, "share_pct": 2.1}], "Tibia": [{"rank": 1, "name": "livedogoes", "viewers": 851, "share_pct": 19.1}, {"rank": 2, "name": "Vda_pedro", "viewers": 361, "share_pct": 8.1}, {"rank": 3, "name": "artilh3iro", "viewers": 351, "share_pct": 7.9}, {"rank": 4, "name": "MassRoon", "viewers": 203, "share_pct": 4.6}, {"rank": 5, "name": "mutilinha", "viewers": 200, "share_pct": 4.5}, {"rank": 6, "name": "Kusnierr", "viewers": 199, "share_pct": 4.5}, {"rank": 7, "name": "Dukoth", "viewers": 191, "share_pct": 4.3}, {"rank": 8, "name": "veyllor", "viewers": 188, "share_pct": 4.2}, {"rank": 9, "name": "Fernando_Fnc", "viewers": 169, "share_pct": 3.8}, {"rank": 10, "name": "Nalkh", "viewers": 165, "share_pct": 3.7}], "Virtual Casino": [{"rank": 1, "name": "Nokan777", "viewers": 1162, "share_pct": 30.6}, {"rank": 2, "name": "gu_strike", "viewers": 946, "share_pct": 24.9}, {"rank": 3, "name": "thayguedess", "viewers": 487, "share_pct": 12.8}, {"rank": 4, "name": "pKennyS", "viewers": 397, "share_pct": 10.4}, {"rank": 5, "name": "sallesbet22", "viewers": 380, "share_pct": 10.0}, {"rank": 6, "name": "vilef0rt", "viewers": 304, "share_pct": 8.0}, {"rank": 7, "name": "krytozin", "viewers": 294, "share_pct": 7.7}, {"rank": 8, "name": "xeiqzin", "viewers": 212, "share_pct": 5.6}, {"rank": 9, "name": "koopicmix_", "viewers": 171, "share_pct": 4.5}, {"rank": 10, "name": "savage7th", "viewers": 170, "share_pct": 4.5}], "ELDEN RING": [{"rank": 1, "name": "pilavpowa", "viewers": 792, "share_pct": 21.7}, {"rank": 2, "name": "Ainrun", "viewers": 482, "share_pct": 13.2}, {"rank": 3, "name": "KEPA_MITA", "viewers": 312, "share_pct": 8.6}, {"rank": 4, "name": "Farore", "viewers": 258, "share_pct": 7.1}, {"rank": 5, "name": "BioticNova", "viewers": 199, "share_pct": 5.5}, {"rank": 6, "name": "Fibi_ch", "viewers": 118, "share_pct": 3.2}, {"rank": 7, "name": "CalmCaleb", "viewers": 117, "share_pct": 3.2}, {"rank": 8, "name": "madara592300", "viewers": 104, "share_pct": 2.9}, {"rank": 9, "name": "Zoodle", "viewers": 89, "share_pct": 2.4}, {"rank": 10, "name": "masterr876", "viewers": 89, "share_pct": 2.4}]}}